{"metadata":[],"pages":[{"margins":{"top":164,"left":56,"bottom":624,"right":518},"box":{"l":0,"t":0,"w":595.92,"h":842.88},"rotation":{"degrees":0,"origin":{"x":0,"y":0},"translation":{"x":0,"y":0}},"pageNumber":1,"elements":[{"id":21,"type":"word","properties":{"isHeader":true},"metadata":[],"box":{"l":57,"t":67.86,"w":136.73,"h":30},"content":"DataSync","font":1,"fontSize":30},{"id":444,"type":"word","properties":{},"metadata":[],"box":{"l":318.36,"t":367.04,"w":45.36,"h":12},"content":"provides","font":2,"fontSize":12},{"id":23,"type":"word","properties":{"isHeader":true},"metadata":[],"box":{"l":259.3,"t":67.86,"w":145.08,"h":30},"content":"Reference","font":1,"fontSize":30},{"id":61,"type":"word","properties":{"isHeader":true},"metadata":[],"box":{"l":57,"t":129.77,"w":38,"h":11.4},"content":"Version","font":3,"fontSize":11.4},{"id":62,"type":"word","properties":{"isHeader":true},"metadata":[],"box":{"l":98.16,"t":129.77,"w":25.34,"h":11.4},"content":"2.1.0","font":3,"fontSize":11.4},{"id":63,"type":"word","properties":{"isHeader":true},"metadata":[],"box":{"l":126.66,"t":129.77,"w":2.96,"h":11.4},"content":"|","font":3,"fontSize":11.4},{"id":64,"type":"word","properties":{"isHeader":true},"metadata":[],"box":{"l":132.78,"t":129.77,"w":21.53,"h":11.4},"content":"Last","font":3,"fontSize":11.4},{"id":65,"type":"word","properties":{"isHeader":true},"metadata":[],"box":{"l":157.47,"t":129.77,"w":46.23,"h":11.4},"content":"Updated:","font":3,"fontSize":11.4},{"id":66,"type":"word","properties":{"isHeader":true},"metadata":[],"box":{"l":206.87,"t":129.77,"w":45.58,"h":11.4},"content":"February","font":3,"fontSize":11.4},{"id":67,"type":"word","properties":{"isHeader":true},"metadata":[],"box":{"l":255.61,"t":129.77,"w":25.35,"h":11.4},"content":"2026","font":3,"fontSize":11.4},{"id":82,"type":"word","properties":{},"metadata":[],"box":{"l":80.25,"t":226.37,"w":16.01,"h":19.2},"content":"1.","font":4,"fontSize":19.2},{"id":83,"type":"word","properties":{},"metadata":[],"box":{"l":101.6,"t":226.37,"w":111.95,"h":19.2},"content":"Introduction","font":4,"fontSize":19.2},{"id":148,"type":"word","properties":{},"metadata":[],"box":{"l":80.25,"t":278.54,"w":49.79,"h":12},"content":"Welcome","font":2,"fontSize":12},{"id":149,"type":"word","properties":{},"metadata":[],"box":{"l":134.7,"t":278.54,"w":10.01,"h":12},"content":"to","font":2,"fontSize":12},{"id":150,"type":"word","properties":{},"metadata":[],"box":{"l":149.35,"t":278.54,"w":16.68,"h":12},"content":"the","font":2,"fontSize":12},{"id":151,"type":"word","properties":{},"metadata":[],"box":{"l":170.69,"t":278.54,"w":52.03,"h":12},"content":"DataSync","font":2,"fontSize":12},{"id":152,"type":"word","properties":{},"metadata":[],"box":{"l":226.71,"t":278.54,"w":19.34,"h":12},"content":"API","font":2,"fontSize":12},{"id":153,"type":"word","properties":{},"metadata":[],"box":{"l":250.7,"t":278.54,"w":82.06,"h":12},"content":"documentation.","font":2,"fontSize":12},{"id":154,"type":"word","properties":{},"metadata":[],"box":{"l":337.41,"t":278.54,"w":52.03,"h":12},"content":"DataSync","font":2,"fontSize":12},{"id":155,"type":"word","properties":{},"metadata":[],"box":{"l":394.08,"t":278.54,"w":8.67,"h":12},"content":"is","font":2,"fontSize":12},{"id":156,"type":"word","properties":{},"metadata":[],"box":{"l":407.4,"t":278.54,"w":6.67,"h":12},"content":"a","font":2,"fontSize":12},{"id":157,"type":"word","properties":{},"metadata":[],"box":{"l":418.73,"t":278.54,"w":48.69,"h":12},"content":"powerful,","font":2,"fontSize":12},{"id":158,"type":"word","properties":{},"metadata":[],"box":{"l":472.07,"t":278.54,"w":44.68,"h":12},"content":"RESTful","font":2,"fontSize":12},{"id":230,"type":"word","properties":{},"metadata":[],"box":{"l":80.25,"t":298.04,"w":19.34,"h":12},"content":"API","font":2,"fontSize":12},{"id":231,"type":"word","properties":{},"metadata":[],"box":{"l":104.17,"t":298.04,"w":20.02,"h":12},"content":"that","font":2,"fontSize":12},{"id":232,"type":"word","properties":{},"metadata":[],"box":{"l":128.76,"t":298.04,"w":42.04,"h":12},"content":"enables","font":2,"fontSize":12},{"id":233,"type":"word","properties":{},"metadata":[],"box":{"l":175.38,"t":298.04,"w":46.68,"h":12},"content":"real-time","font":2,"fontSize":12},{"id":234,"type":"word","properties":{},"metadata":[],"box":{"l":226.63,"t":298.04,"w":23.36,"h":12},"content":"data","font":2,"fontSize":12},{"id":235,"type":"word","properties":{},"metadata":[],"box":{"l":254.56,"t":298.04,"w":83.38,"h":12},"content":"synchronization","font":2,"fontSize":12},{"id":236,"type":"word","properties":{},"metadata":[],"box":{"l":342.52,"t":298.04,"w":35.34,"h":12},"content":"across","font":2,"fontSize":12},{"id":237,"type":"word","properties":{},"metadata":[],"box":{"l":382.44,"t":298.04,"w":55.36,"h":12},"content":"distributed","font":2,"fontSize":12},{"id":238,"type":"word","properties":{},"metadata":[],"box":{"l":442.38,"t":298.04,"w":47.34,"h":12},"content":"systems.","font":2,"fontSize":12},{"id":239,"type":"word","properties":{},"metadata":[],"box":{"l":494.08,"t":298.04,"w":22.67,"h":12},"content":"This","font":2,"fontSize":12},{"id":308,"type":"word","properties":{},"metadata":[],"box":{"l":80.25,"t":316.79,"w":78.72,"h":12},"content":"documentation","font":2,"fontSize":12},{"id":309,"type":"word","properties":{},"metadata":[],"box":{"l":164.82,"t":316.79,"w":45.36,"h":12},"content":"provides","font":2,"fontSize":12},{"id":310,"type":"word","properties":{},"metadata":[],"box":{"l":216.02,"t":316.79,"w":81.37,"h":12},"content":"comprehensive","font":2,"fontSize":12},{"id":311,"type":"word","properties":{},"metadata":[],"box":{"l":303.24,"t":316.79,"w":48.71,"h":12},"content":"guidance","font":2,"fontSize":12},{"id":312,"type":"word","properties":{},"metadata":[],"box":{"l":357.79,"t":316.79,"w":14,"h":12},"content":"for","font":2,"fontSize":12},{"id":313,"type":"word","properties":{},"metadata":[],"box":{"l":377.64,"t":316.79,"w":56.04,"h":12},"content":"integrating","font":2,"fontSize":12},{"id":314,"type":"word","properties":{},"metadata":[],"box":{"l":439.53,"t":316.79,"w":52.02,"h":12},"content":"DataSync","font":2,"fontSize":12},{"id":315,"type":"word","properties":{},"metadata":[],"box":{"l":497.4,"t":316.79,"w":19.35,"h":12},"content":"into","font":2,"fontSize":12},{"id":364,"type":"word","properties":{},"metadata":[],"box":{"l":80.25,"t":336.29,"w":23.34,"h":12},"content":"your","font":2,"fontSize":12},{"id":365,"type":"word","properties":{},"metadata":[],"box":{"l":106.93,"t":336.29,"w":63.38,"h":12},"content":"applications","font":2,"fontSize":12},{"id":366,"type":"word","properties":{},"metadata":[],"box":{"l":173.64,"t":336.29,"w":20.02,"h":12},"content":"and","font":2,"fontSize":12},{"id":367,"type":"word","properties":{},"metadata":[],"box":{"l":196.99,"t":336.29,"w":52.71,"h":12},"content":"managing","font":2,"fontSize":12},{"id":368,"type":"word","properties":{},"metadata":[],"box":{"l":253.03,"t":336.29,"w":23.36,"h":12},"content":"data","font":2,"fontSize":12},{"id":369,"type":"word","properties":{},"metadata":[],"box":{"l":279.72,"t":336.29,"w":52.68,"h":12},"content":"workflows","font":2,"fontSize":12},{"id":370,"type":"word","properties":{},"metadata":[],"box":{"l":335.73,"t":336.29,"w":10.01,"h":12},"content":"at","font":2,"fontSize":12},{"id":371,"type":"word","properties":{},"metadata":[],"box":{"l":349.07,"t":336.29,"w":31.35,"h":12},"content":"scale.","font":2,"fontSize":12},{"id":439,"type":"word","properties":{},"metadata":[],"box":{"l":80.25,"t":367.04,"w":52.03,"h":12},"content":"DataSync","font":2,"fontSize":12},{"id":440,"type":"word","properties":{},"metadata":[],"box":{"l":138.68,"t":367.04,"w":46.03,"h":12},"content":"supports","font":2,"fontSize":12},{"id":441,"type":"word","properties":{},"metadata":[],"box":{"l":191.11,"t":367.04,"w":41.35,"h":12},"content":"multiple","font":2,"fontSize":12},{"id":442,"type":"word","properties":{},"metadata":[],"box":{"l":238.86,"t":367.04,"w":23.36,"h":12},"content":"data","font":2,"fontSize":12},{"id":443,"type":"word","properties":{},"metadata":[],"box":{"l":268.62,"t":367.04,"w":43.34,"h":12},"content":"formats,","font":2,"fontSize":12},{"id":797,"type":"word","properties":{},"metadata":[],"box":{"l":477.08,"t":526.79,"w":24.67,"h":12},"content":"sync","font":5,"fontSize":12},{"id":445,"type":"word","properties":{},"metadata":[],"box":{"l":370.12,"t":367.04,"w":33.35,"h":12},"content":"robust","font":2,"fontSize":12},{"id":446,"type":"word","properties":{},"metadata":[],"box":{"l":409.88,"t":367.04,"w":25.34,"h":12},"content":"error","font":2,"fontSize":12},{"id":447,"type":"word","properties":{},"metadata":[],"box":{"l":441.62,"t":367.04,"w":48.71,"h":12},"content":"handling,","font":2,"fontSize":12},{"id":448,"type":"word","properties":{},"metadata":[],"box":{"l":496.73,"t":367.04,"w":20.02,"h":12},"content":"and","font":2,"fontSize":12},{"id":515,"type":"word","properties":{},"metadata":[],"box":{"l":80.25,"t":385.79,"w":44.03,"h":12},"content":"includes","font":2,"fontSize":12},{"id":516,"type":"word","properties":{},"metadata":[],"box":{"l":131.35,"t":385.79,"w":35.35,"h":12},"content":"built-in","font":2,"fontSize":12},{"id":517,"type":"word","properties":{},"metadata":[],"box":{"l":173.78,"t":385.79,"w":24,"h":12},"content":"retry","font":2,"fontSize":12},{"id":518,"type":"word","properties":{},"metadata":[],"box":{"l":204.85,"t":385.79,"w":70.69,"h":12},"content":"mechanisms.","font":2,"fontSize":12},{"id":519,"type":"word","properties":{},"metadata":[],"box":{"l":282.61,"t":385.79,"w":24,"h":12},"content":"With","font":2,"fontSize":12},{"id":520,"type":"word","properties":{},"metadata":[],"box":{"l":313.69,"t":385.79,"w":40.02,"h":12},"content":"support","font":2,"fontSize":12},{"id":521,"type":"word","properties":{},"metadata":[],"box":{"l":360.79,"t":385.79,"w":14,"h":12},"content":"for","font":2,"fontSize":12},{"id":522,"type":"word","properties":{},"metadata":[],"box":{"l":381.87,"t":385.79,"w":54.04,"h":12},"content":"webhooks","font":2,"fontSize":12},{"id":523,"type":"word","properties":{},"metadata":[],"box":{"l":442.98,"t":385.79,"w":20.02,"h":12},"content":"and","font":2,"fontSize":12},{"id":524,"type":"word","properties":{},"metadata":[],"box":{"l":470.07,"t":385.79,"w":46.68,"h":12},"content":"real-time","font":2,"fontSize":12},{"id":596,"type":"word","properties":{},"metadata":[],"box":{"l":80.25,"t":405.29,"w":66.7,"h":12},"content":"notifications,","font":2,"fontSize":12},{"id":597,"type":"word","properties":{},"metadata":[],"box":{"l":152.54,"t":405.29,"w":19.35,"h":12},"content":"you","font":2,"fontSize":12},{"id":598,"type":"word","properties":{},"metadata":[],"box":{"l":177.47,"t":405.29,"w":19.35,"h":12},"content":"can","font":2,"fontSize":12},{"id":599,"type":"word","properties":{},"metadata":[],"box":{"l":202.4,"t":405.29,"w":25.35,"h":12},"content":"build","font":2,"fontSize":12},{"id":600,"type":"word","properties":{},"metadata":[],"box":{"l":233.34,"t":405.29,"w":58.03,"h":12},"content":"responsive","font":2,"fontSize":12},{"id":601,"type":"word","properties":{},"metadata":[],"box":{"l":296.96,"t":405.29,"w":63.38,"h":12},"content":"applications","font":2,"fontSize":12},{"id":602,"type":"word","properties":{},"metadata":[],"box":{"l":365.92,"t":405.29,"w":20.02,"h":12},"content":"that","font":2,"fontSize":12},{"id":603,"type":"word","properties":{},"metadata":[],"box":{"l":391.52,"t":405.29,"w":22.01,"h":12},"content":"stay","font":2,"fontSize":12},{"id":604,"type":"word","properties":{},"metadata":[],"box":{"l":419.11,"t":405.29,"w":70.71,"h":12},"content":"synchronized","font":2,"fontSize":12},{"id":605,"type":"word","properties":{},"metadata":[],"box":{"l":495.4,"t":405.29,"w":21.34,"h":12},"content":"with","font":2,"fontSize":12},{"id":622,"type":"word","properties":{},"metadata":[],"box":{"l":80.25,"t":424.04,"w":23.34,"h":12},"content":"your","font":2,"fontSize":12},{"id":623,"type":"word","properties":{},"metadata":[],"box":{"l":106.93,"t":424.04,"w":23.35,"h":12},"content":"data","font":2,"fontSize":12},{"id":624,"type":"word","properties":{},"metadata":[],"box":{"l":133.62,"t":424.04,"w":45.35,"h":12},"content":"sources.","font":2,"fontSize":12},{"id":639,"type":"word","properties":{},"metadata":[],"box":{"l":98.25,"t":481.04,"w":41.99,"h":12},"content":"Getting","font":6,"fontSize":12},{"id":640,"type":"word","properties":{},"metadata":[],"box":{"l":143.58,"t":481.04,"w":41.34,"h":12},"content":"Started","font":6,"fontSize":12},{"id":650,"type":"word","properties":{},"metadata":[],"box":{"l":98.25,"t":546.29,"w":48.7,"h":12},"content":"behavior.","font":5,"fontSize":12},{"id":712,"type":"word","properties":{},"metadata":[],"box":{"l":98.25,"t":508.04,"w":24.01,"h":12},"content":"New","font":5,"fontSize":12},{"id":713,"type":"word","properties":{},"metadata":[],"box":{"l":128.09,"t":508.04,"w":10.01,"h":12},"content":"to","font":5,"fontSize":12},{"id":714,"type":"word","properties":{},"metadata":[],"box":{"l":143.93,"t":508.04,"w":58.7,"h":12},"content":"DataSync?","font":5,"fontSize":12},{"id":715,"type":"word","properties":{},"metadata":[],"box":{"l":208.46,"t":508.04,"w":25.34,"h":12},"content":"Start","font":5,"fontSize":12},{"id":716,"type":"word","properties":{},"metadata":[],"box":{"l":239.63,"t":508.04,"w":21.34,"h":12},"content":"with","font":5,"fontSize":12},{"id":717,"type":"word","properties":{},"metadata":[],"box":{"l":266.81,"t":508.04,"w":16.68,"h":12},"content":"the","font":5,"fontSize":12},{"id":718,"type":"word","properties":{},"metadata":[],"box":{"l":289.32,"t":508.04,"w":57.37,"h":12},"content":"Installation","font":7,"fontSize":12},{"id":719,"type":"word","properties":{},"metadata":[],"box":{"l":352.53,"t":508.04,"w":38.02,"h":12},"content":"section","font":5,"fontSize":12},{"id":720,"type":"word","properties":{},"metadata":[],"box":{"l":396.39,"t":508.04,"w":10.01,"h":12},"content":"to","font":5,"fontSize":12},{"id":721,"type":"word","properties":{},"metadata":[],"box":{"l":412.23,"t":508.04,"w":16.01,"h":12},"content":"set","font":5,"fontSize":12},{"id":722,"type":"word","properties":{},"metadata":[],"box":{"l":434.06,"t":508.04,"w":13.35,"h":12},"content":"up","font":5,"fontSize":12},{"id":723,"type":"word","properties":{},"metadata":[],"box":{"l":453.24,"t":508.04,"w":23.34,"h":12},"content":"your","font":5,"fontSize":12},{"id":724,"type":"word","properties":{},"metadata":[],"box":{"l":482.42,"t":508.04,"w":19.33,"h":12},"content":"first","font":5,"fontSize":12},{"id":788,"type":"word","properties":{},"metadata":[],"box":{"l":98.25,"t":526.79,"w":61.38,"h":12},"content":"connection,","font":5,"fontSize":12},{"id":789,"type":"word","properties":{},"metadata":[],"box":{"l":164.73,"t":526.79,"w":23.36,"h":12},"content":"then","font":5,"fontSize":12},{"id":790,"type":"word","properties":{},"metadata":[],"box":{"l":193.2,"t":526.79,"w":34.68,"h":12},"content":"review","font":5,"fontSize":12},{"id":791,"type":"word","properties":{},"metadata":[],"box":{"l":232.98,"t":526.79,"w":16.68,"h":12},"content":"the","font":5,"fontSize":12},{"id":792,"type":"word","properties":{},"metadata":[],"box":{"l":254.78,"t":526.79,"w":71.38,"h":12},"content":"Configuration","font":7,"fontSize":12},{"id":793,"type":"word","properties":{},"metadata":[],"box":{"l":331.26,"t":526.79,"w":38.02,"h":12},"content":"section","font":5,"fontSize":12},{"id":794,"type":"word","properties":{},"metadata":[],"box":{"l":374.39,"t":526.79,"w":10.01,"h":12},"content":"to","font":5,"fontSize":12},{"id":795,"type":"word","properties":{},"metadata":[],"box":{"l":389.51,"t":526.79,"w":54.02,"h":12},"content":"customize","font":5,"fontSize":12},{"id":796,"type":"word","properties":{},"metadata":[],"box":{"l":448.63,"t":526.79,"w":23.34,"h":12},"content":"your","font":5,"fontSize":12},{"id":22,"type":"word","properties":{"isHeader":true},"metadata":[],"box":{"l":200.95,"t":67.86,"w":50.01,"h":30},"content":"API","font":1,"fontSize":30}]},{"margins":{"top":164,"left":56,"bottom":624,"right":518},"box":{"l":0,"t":0,"w":595.92,"h":842.88},"rotation":{"degrees":0,"origin":{"x":0,"y":0},"translation":{"x":0,"y":0}},"pageNumber":2,"elements":[{"id":812,"type":"word","properties":{"isHeader":true},"metadata":[],"box":{"l":80.25,"t":116.87,"w":16.01,"h":19.2},"content":"2.","font":4,"fontSize":19.2},{"id":1216,"type":"word","properties":{},"metadata":[],"box":{"l":80.25,"t":434.15,"w":79.18,"h":14.4},"content":"Kubernetes","font":8,"fontSize":14.4},{"id":832,"type":"word","properties":{},"metadata":[],"box":{"l":80.25,"t":169.04,"w":47.36,"h":12},"content":"Installing","font":2,"fontSize":12},{"id":833,"type":"word","properties":{},"metadata":[],"box":{"l":138.99,"t":169.04,"w":52.03,"h":12},"content":"DataSync","font":2,"fontSize":12},{"id":880,"type":"word","properties":{},"metadata":[],"box":{"l":202.39,"t":169.04,"w":8.67,"h":12},"content":"is","font":2,"fontSize":12},{"id":881,"type":"word","properties":{},"metadata":[],"box":{"l":222.44,"t":169.04,"w":79.37,"h":12},"content":"straightforward","font":2,"fontSize":12},{"id":882,"type":"word","properties":{},"metadata":[],"box":{"l":313.18,"t":169.04,"w":20.02,"h":12},"content":"and","font":2,"fontSize":12},{"id":883,"type":"word","properties":{},"metadata":[],"box":{"l":344.58,"t":169.04,"w":46.03,"h":12},"content":"supports","font":2,"fontSize":12},{"id":884,"type":"word","properties":{},"metadata":[],"box":{"l":401.98,"t":169.04,"w":41.35,"h":12},"content":"multiple","font":2,"fontSize":12},{"id":885,"type":"word","properties":{},"metadata":[],"box":{"l":454.71,"t":169.04,"w":62.04,"h":12},"content":"deployment","font":2,"fontSize":12},{"id":952,"type":"word","properties":{},"metadata":[],"box":{"l":80.25,"t":188.54,"w":72.04,"h":12},"content":"environments","font":2,"fontSize":12},{"id":953,"type":"word","properties":{},"metadata":[],"box":{"l":155.62,"t":188.54,"w":47.37,"h":12},"content":"including","font":2,"fontSize":12},{"id":954,"type":"word","properties":{},"metadata":[],"box":{"l":206.32,"t":188.54,"w":40.68,"h":12},"content":"Docker,","font":2,"fontSize":12},{"id":955,"type":"word","properties":{},"metadata":[],"box":{"l":250.34,"t":188.54,"w":64.71,"h":12},"content":"Kubernetes,","font":2,"fontSize":12},{"id":956,"type":"word","properties":{},"metadata":[],"box":{"l":318.38,"t":188.54,"w":20.02,"h":12},"content":"and","font":2,"fontSize":12},{"id":957,"type":"word","properties":{},"metadata":[],"box":{"l":341.74,"t":188.54,"w":52.03,"h":12},"content":"traditional","font":2,"fontSize":12},{"id":958,"type":"word","properties":{},"metadata":[],"box":{"l":397.1,"t":188.54,"w":33.34,"h":12},"content":"server","font":2,"fontSize":12},{"id":959,"type":"word","properties":{},"metadata":[],"box":{"l":433.78,"t":188.54,"w":38.69,"h":12},"content":"setups.","font":2,"fontSize":12},{"id":978,"type":"word","properties":{},"metadata":[],"box":{"l":80.25,"t":226.4,"w":48.8,"h":14.4},"content":"Docker","font":8,"fontSize":14.4},{"id":979,"type":"word","properties":{},"metadata":[],"box":{"l":133.04,"t":226.4,"w":75.96,"h":14.4},"content":"Installation","font":8,"fontSize":14.4},{"id":1035,"type":"word","properties":{},"metadata":[],"box":{"l":80.25,"t":260.54,"w":20.68,"h":12},"content":"The","font":2,"fontSize":12},{"id":1036,"type":"word","properties":{},"metadata":[],"box":{"l":104.26,"t":260.54,"w":38.02,"h":12},"content":"easiest","font":2,"fontSize":12},{"id":1037,"type":"word","properties":{},"metadata":[],"box":{"l":145.62,"t":260.54,"w":21.34,"h":12},"content":"way","font":2,"fontSize":12},{"id":1038,"type":"word","properties":{},"metadata":[],"box":{"l":170.29,"t":260.54,"w":10.01,"h":12},"content":"to","font":2,"fontSize":12},{"id":1039,"type":"word","properties":{},"metadata":[],"box":{"l":183.63,"t":260.54,"w":16.68,"h":12},"content":"get","font":2,"fontSize":12},{"id":1040,"type":"word","properties":{},"metadata":[],"box":{"l":203.65,"t":260.54,"w":36.69,"h":12},"content":"started","font":2,"fontSize":12},{"id":1041,"type":"word","properties":{},"metadata":[],"box":{"l":243.67,"t":260.54,"w":8.67,"h":12},"content":"is","font":2,"fontSize":12},{"id":1042,"type":"word","properties":{},"metadata":[],"box":{"l":255.67,"t":260.54,"w":28.69,"h":12},"content":"using","font":2,"fontSize":12},{"id":1043,"type":"word","properties":{},"metadata":[],"box":{"l":287.69,"t":260.54,"w":16.68,"h":12},"content":"the","font":2,"fontSize":12},{"id":1044,"type":"word","properties":{},"metadata":[],"box":{"l":307.71,"t":260.54,"w":33.8,"h":12},"content":"official","font":2,"fontSize":12},{"id":1045,"type":"word","properties":{},"metadata":[],"box":{"l":344.84,"t":260.54,"w":38.01,"h":12},"content":"Docker","font":2,"fontSize":12},{"id":1046,"type":"word","properties":{},"metadata":[],"box":{"l":386.18,"t":260.54,"w":36.02,"h":12},"content":"image:","font":2,"fontSize":12},{"id":1072,"type":"word","properties":{},"metadata":[],"box":{"l":95.25,"t":308.19,"w":38.87,"h":10.8},"content":"docker","font":9,"fontSize":10.8},{"id":1073,"type":"word","properties":{},"metadata":[],"box":{"l":140.59,"t":308.19,"w":25.91,"h":10.8},"content":"pull","font":9,"fontSize":10.8},{"id":1074,"type":"word","properties":{},"metadata":[],"box":{"l":172.97,"t":308.19,"w":97.16,"h":10.8},"content":"datasync:latest","font":9,"fontSize":10.8},{"id":1087,"type":"word","properties":{},"metadata":[],"box":{"l":95.25,"t":323.94,"w":38.87,"h":10.8},"content":"docker","font":9,"fontSize":10.8},{"id":1088,"type":"word","properties":{},"metadata":[],"box":{"l":140.59,"t":323.94,"w":19.44,"h":10.8},"content":"run","font":9,"fontSize":10.8},{"id":1089,"type":"word","properties":{},"metadata":[],"box":{"l":166.5,"t":323.94,"w":12.96,"h":10.8},"content":"-d","font":9,"fontSize":10.8},{"id":1090,"type":"word","properties":{},"metadata":[],"box":{"l":185.93,"t":323.94,"w":6.48,"h":10.8},"content":"\\","font":9,"fontSize":10.8},{"id":1103,"type":"word","properties":{},"metadata":[],"box":{"l":108.2,"t":338.94,"w":12.96,"h":10.8},"content":"-p","font":9,"fontSize":10.8},{"id":1104,"type":"word","properties":{},"metadata":[],"box":{"l":127.63,"t":338.94,"w":58.3,"h":10.8},"content":"8080:8080","font":9,"fontSize":10.8},{"id":1105,"type":"word","properties":{},"metadata":[],"box":{"l":192.4,"t":338.94,"w":6.48,"h":10.8},"content":"\\","font":9,"fontSize":10.8},{"id":1129,"type":"word","properties":{},"metadata":[],"box":{"l":108.2,"t":353.94,"w":12.96,"h":10.8},"content":"-e","font":9,"fontSize":10.8},{"id":1130,"type":"word","properties":{},"metadata":[],"box":{"l":127.63,"t":353.94,"w":129.54,"h":10.8},"content":"API_KEY=your-api-key","font":9,"fontSize":10.8},{"id":1131,"type":"word","properties":{},"metadata":[],"box":{"l":263.65,"t":353.94,"w":6.48,"h":10.8},"content":"\\","font":9,"fontSize":10.8},{"id":1177,"type":"word","properties":{},"metadata":[],"box":{"l":108.2,"t":368.94,"w":12.96,"h":10.8},"content":"-e","font":9,"fontSize":10.8},{"id":1178,"type":"word","properties":{},"metadata":[],"box":{"l":127.63,"t":368.94,"w":272.03,"h":10.8},"content":"DB_URL=postgresql://user:pass@db:5432/sync","font":9,"fontSize":10.8},{"id":1179,"type":"word","properties":{},"metadata":[],"box":{"l":406.14,"t":368.94,"w":6.48,"h":10.8},"content":"\\","font":9,"fontSize":10.8},{"id":1195,"type":"word","properties":{},"metadata":[],"box":{"l":108.2,"t":383.94,"w":97.16,"h":10.8},"content":"datasync:latest","font":9,"fontSize":10.8},{"id":1621,"type":"word","properties":{"isFooter":true},"metadata":[],"box":{"l":176.97,"t":695.54,"w":44.01,"h":12},"content":"Secrets.","font":10,"fontSize":12},{"id":1217,"type":"word","properties":{},"metadata":[],"box":{"l":163.42,"t":434.15,"w":82.36,"h":14.4},"content":"Deployment","font":8,"fontSize":14.4},{"id":1268,"type":"word","properties":{},"metadata":[],"box":{"l":80.25,"t":468.29,"w":18,"h":12},"content":"For","font":2,"fontSize":12},{"id":1269,"type":"word","properties":{},"metadata":[],"box":{"l":101.58,"t":468.29,"w":61.38,"h":12},"content":"Kubernetes","font":2,"fontSize":12},{"id":1270,"type":"word","properties":{},"metadata":[],"box":{"l":166.3,"t":468.29,"w":75.37,"h":12},"content":"environments,","font":2,"fontSize":12},{"id":1271,"type":"word","properties":{},"metadata":[],"box":{"l":245,"t":468.29,"w":19.35,"h":12},"content":"use","font":2,"fontSize":12},{"id":1272,"type":"word","properties":{},"metadata":[],"box":{"l":267.68,"t":468.29,"w":16.68,"h":12},"content":"the","font":2,"fontSize":12},{"id":1273,"type":"word","properties":{},"metadata":[],"box":{"l":287.7,"t":468.29,"w":33.8,"h":12},"content":"official","font":2,"fontSize":12},{"id":1274,"type":"word","properties":{},"metadata":[],"box":{"l":324.83,"t":468.29,"w":28,"h":12},"content":"Helm","font":2,"fontSize":12},{"id":1275,"type":"word","properties":{},"metadata":[],"box":{"l":356.16,"t":468.29,"w":30.01,"h":12},"content":"chart:","font":2,"fontSize":12},{"id":1321,"type":"word","properties":{},"metadata":[],"box":{"l":95.25,"t":516.69,"w":25.91,"h":10.8},"content":"helm","font":9,"fontSize":10.8},{"id":1322,"type":"word","properties":{},"metadata":[],"box":{"l":127.63,"t":516.69,"w":25.91,"h":10.8},"content":"repo","font":9,"fontSize":10.8},{"id":1323,"type":"word","properties":{},"metadata":[],"box":{"l":160.02,"t":516.69,"w":19.44,"h":10.8},"content":"add","font":9,"fontSize":10.8},{"id":1324,"type":"word","properties":{},"metadata":[],"box":{"l":185.93,"t":516.69,"w":51.82,"h":10.8},"content":"datasync","font":9,"fontSize":10.8},{"id":1325,"type":"word","properties":{},"metadata":[],"box":{"l":244.22,"t":516.69,"w":168.4,"h":10.8},"content":"https://charts.datasync.io","font":9,"fontSize":10.8},{"id":1363,"type":"word","properties":{},"metadata":[],"box":{"l":95.25,"t":531.69,"w":25.91,"h":10.8},"content":"helm","font":9,"fontSize":10.8},{"id":1364,"type":"word","properties":{},"metadata":[],"box":{"l":127.63,"t":531.69,"w":45.34,"h":10.8},"content":"install","font":9,"fontSize":10.8},{"id":1365,"type":"word","properties":{},"metadata":[],"box":{"l":179.45,"t":531.69,"w":51.82,"h":10.8},"content":"datasync","font":9,"fontSize":10.8},{"id":1366,"type":"word","properties":{},"metadata":[],"box":{"l":237.74,"t":531.69,"w":110.11,"h":10.8},"content":"datasync/datasync","font":9,"fontSize":10.8},{"id":1367,"type":"word","properties":{},"metadata":[],"box":{"l":354.32,"t":531.69,"w":6.48,"h":10.8},"content":"\\","font":9,"fontSize":10.8},{"id":1393,"type":"word","properties":{},"metadata":[],"box":{"l":108.2,"t":546.69,"w":32.39,"h":10.8},"content":"--set","font":9,"fontSize":10.8},{"id":1394,"type":"word","properties":{},"metadata":[],"box":{"l":147.07,"t":546.69,"w":123.06,"h":10.8},"content":"apiKey=your-api-key","font":9,"fontSize":10.8},{"id":1395,"type":"word","properties":{},"metadata":[],"box":{"l":276.6,"t":546.69,"w":6.48,"h":10.8},"content":"\\","font":9,"fontSize":10.8},{"id":1439,"type":"word","properties":{},"metadata":[],"box":{"l":108.2,"t":561.69,"w":32.39,"h":10.8},"content":"--set","font":9,"fontSize":10.8},{"id":1440,"type":"word","properties":{},"metadata":[],"box":{"l":147.07,"t":561.69,"w":246.12,"h":10.8},"content":"database.url=postgresql://db:5432/sync","font":9,"fontSize":10.8},{"id":1456,"type":"word","properties":{"isFooter":true},"metadata":[],"box":{"l":98.25,"t":630.29,"w":47.35,"h":12},"content":"Security","font":11,"fontSize":12},{"id":1457,"type":"word","properties":{"isFooter":true},"metadata":[],"box":{"l":148.94,"t":630.29,"w":47.55,"h":12},"content":"Warning","font":11,"fontSize":12},{"id":1518,"type":"word","properties":{"isFooter":true},"metadata":[],"box":{"l":98.25,"t":657.29,"w":32.01,"h":12},"content":"Never","font":10,"fontSize":12},{"id":1519,"type":"word","properties":{"isFooter":true},"metadata":[],"box":{"l":135.8,"t":657.29,"w":38.67,"h":12},"content":"commit","font":10,"fontSize":12},{"id":1520,"type":"word","properties":{"isFooter":true},"metadata":[],"box":{"l":179.34,"t":657.29,"w":19.34,"h":12},"content":"API","font":10,"fontSize":12},{"id":1521,"type":"word","properties":{"isFooter":true},"metadata":[],"box":{"l":204.21,"t":657.29,"w":24.67,"h":12},"content":"keys","font":10,"fontSize":12},{"id":1522,"type":"word","properties":{"isFooter":true},"metadata":[],"box":{"l":234.42,"t":657.29,"w":10.01,"h":12},"content":"to","font":10,"fontSize":12},{"id":1523,"type":"word","properties":{"isFooter":true},"metadata":[],"box":{"l":249.97,"t":657.29,"w":38.68,"h":12},"content":"version","font":10,"fontSize":12},{"id":1524,"type":"word","properties":{"isFooter":true},"metadata":[],"box":{"l":294.19,"t":657.29,"w":39.35,"h":12},"content":"control.","font":10,"fontSize":12},{"id":1525,"type":"word","properties":{"isFooter":true},"metadata":[],"box":{"l":339.07,"t":657.29,"w":21.34,"h":12},"content":"Use","font":10,"fontSize":12},{"id":1526,"type":"word","properties":{"isFooter":true},"metadata":[],"box":{"l":365.95,"t":657.29,"w":66.04,"h":12},"content":"environment","font":10,"fontSize":12},{"id":1527,"type":"word","properties":{"isFooter":true},"metadata":[],"box":{"l":437.52,"t":657.29,"w":48.02,"h":12},"content":"variables","font":10,"fontSize":12},{"id":1528,"type":"word","properties":{"isFooter":true},"metadata":[],"box":{"l":491.08,"t":657.29,"w":10.67,"h":12},"content":"or","font":10,"fontSize":12},{"id":1590,"type":"word","properties":{"isFooter":true},"metadata":[],"box":{"l":98.25,"t":676.79,"w":38.68,"h":12},"content":"secrets","font":10,"fontSize":12},{"id":1591,"type":"word","properties":{"isFooter":true},"metadata":[],"box":{"l":140.6,"t":676.79,"w":70.04,"h":12},"content":"management","font":10,"fontSize":12},{"id":1592,"type":"word","properties":{"isFooter":true},"metadata":[],"box":{"l":214.31,"t":676.79,"w":44,"h":12},"content":"systems","font":10,"fontSize":12},{"id":1593,"type":"word","properties":{"isFooter":true},"metadata":[],"box":{"l":261.98,"t":676.79,"w":18,"h":12},"content":"like","font":10,"fontSize":12},{"id":1594,"type":"word","properties":{"isFooter":true},"metadata":[],"box":{"l":283.65,"t":676.79,"w":56.69,"h":12},"content":"HashiCorp","font":10,"fontSize":12},{"id":1595,"type":"word","properties":{"isFooter":true},"metadata":[],"box":{"l":344.01,"t":676.79,"w":29.8,"h":12},"content":"Vault,","font":10,"fontSize":12},{"id":1596,"type":"word","properties":{"isFooter":true},"metadata":[],"box":{"l":376.81,"t":676.79,"w":26.89,"h":12},"content":"AWS","font":10,"fontSize":12},{"id":1597,"type":"word","properties":{"isFooter":true},"metadata":[],"box":{"l":407.37,"t":676.79,"w":40.68,"h":12},"content":"Secrets","font":10,"fontSize":12},{"id":1598,"type":"word","properties":{"isFooter":true},"metadata":[],"box":{"l":451.72,"t":676.79,"w":50.03,"h":12},"content":"Manager,","font":10,"fontSize":12},{"id":1619,"type":"word","properties":{"isFooter":true},"metadata":[],"box":{"l":98.25,"t":695.54,"w":10.67,"h":12},"content":"or","font":10,"fontSize":12},{"id":1620,"type":"word","properties":{"isFooter":true},"metadata":[],"box":{"l":112.25,"t":695.54,"w":61.38,"h":12},"content":"Kubernetes","font":10,"fontSize":12},{"id":813,"type":"word","properties":{"isHeader":true},"metadata":[],"box":{"l":101.6,"t":116.87,"w":101.32,"h":19.2},"content":"Installation","font":4,"fontSize":19.2}]},{"margins":{"top":164,"left":56,"bottom":624,"right":518},"box":{"l":0,"t":0,"w":595.92,"h":842.88},"rotation":{"degrees":0,"origin":{"x":0,"y":0},"translation":{"x":0,"y":0}},"pageNumber":3,"elements":[{"id":1686,"type":"word","properties":{},"metadata":[],"box":{"l":80.25,"t":169.04,"w":52.03,"h":12},"content":"DataSync","font":2,"fontSize":12},{"id":2038,"type":"word","properties":{},"metadata":[],"box":{"l":107.25,"t":364.35,"w":93.62,"h":12},"content":"SYNC_INTERVAL","font":12,"fontSize":12},{"id":1688,"type":"word","properties":{},"metadata":[],"box":{"l":213.67,"t":169.04,"w":8.67,"h":12},"content":"is","font":2,"fontSize":12},{"id":1689,"type":"word","properties":{},"metadata":[],"box":{"l":228.67,"t":169.04,"w":50.04,"h":12},"content":"managed","font":2,"fontSize":12},{"id":1690,"type":"word","properties":{},"metadata":[],"box":{"l":285.05,"t":169.04,"w":40.7,"h":12},"content":"through","font":2,"fontSize":12},{"id":1691,"type":"word","properties":{},"metadata":[],"box":{"l":332.08,"t":169.04,"w":66.04,"h":12},"content":"environment","font":2,"fontSize":12},{"id":1692,"type":"word","properties":{},"metadata":[],"box":{"l":404.46,"t":169.04,"w":48.02,"h":12},"content":"variables","font":2,"fontSize":12},{"id":1693,"type":"word","properties":{},"metadata":[],"box":{"l":458.82,"t":169.04,"w":20.02,"h":12},"content":"and","font":2,"fontSize":12},{"id":1694,"type":"word","properties":{},"metadata":[],"box":{"l":484.96,"t":169.04,"w":31.79,"h":12},"content":"YAML","font":2,"fontSize":12},{"id":1770,"type":"word","properties":{},"metadata":[],"box":{"l":80.25,"t":188.54,"w":68.71,"h":12},"content":"configuration","font":2,"fontSize":12},{"id":1771,"type":"word","properties":{},"metadata":[],"box":{"l":153.09,"t":188.54,"w":24.67,"h":12},"content":"files.","font":2,"fontSize":12},{"id":1772,"type":"word","properties":{},"metadata":[],"box":{"l":181.68,"t":188.54,"w":20.68,"h":12},"content":"The","font":2,"fontSize":12},{"id":1773,"type":"word","properties":{},"metadata":[],"box":{"l":206.49,"t":188.54,"w":38,"h":12},"content":"system","font":2,"fontSize":12},{"id":1774,"type":"word","properties":{},"metadata":[],"box":{"l":248.63,"t":188.54,"w":46.02,"h":12},"content":"supports","font":2,"fontSize":12},{"id":1775,"type":"word","properties":{},"metadata":[],"box":{"l":298.78,"t":188.54,"w":54.03,"h":12},"content":"hot-reload","font":2,"fontSize":12},{"id":1776,"type":"word","properties":{},"metadata":[],"box":{"l":356.95,"t":188.54,"w":10.01,"h":12},"content":"of","font":2,"fontSize":12},{"id":1777,"type":"word","properties":{},"metadata":[],"box":{"l":371.09,"t":188.54,"w":58.02,"h":12},"content":"non-critical","font":2,"fontSize":12},{"id":1778,"type":"word","properties":{},"metadata":[],"box":{"l":433.24,"t":188.54,"w":41.36,"h":12},"content":"settings","font":2,"fontSize":12},{"id":1779,"type":"word","properties":{},"metadata":[],"box":{"l":478.72,"t":188.54,"w":38.02,"h":12},"content":"without","font":2,"fontSize":12},{"id":1795,"type":"word","properties":{"isHeader":true},"metadata":[],"box":{"l":80.25,"t":116.87,"w":16.01,"h":19.2},"content":"3.","font":4,"fontSize":19.2},{"id":1796,"type":"word","properties":{"isHeader":true},"metadata":[],"box":{"l":101.6,"t":116.87,"w":125.81,"h":19.2},"content":"Configuration","font":4,"fontSize":19.2},{"id":1817,"type":"word","properties":{},"metadata":[],"box":{"l":80.25,"t":207.29,"w":38.01,"h":12},"content":"service","font":2,"fontSize":12},{"id":1818,"type":"word","properties":{},"metadata":[],"box":{"l":121.59,"t":207.29,"w":63.37,"h":12},"content":"interruption.","font":2,"fontSize":12},{"id":1839,"type":"word","properties":{},"metadata":[],"box":{"l":80.25,"t":245.9,"w":87.96,"h":14.4},"content":"Environment","font":8,"fontSize":14.4},{"id":1840,"type":"word","properties":{},"metadata":[],"box":{"l":172.2,"t":245.9,"w":63.21,"h":14.4},"content":"Variables","font":8,"fontSize":14.4},{"id":1878,"type":"word","properties":{},"metadata":[],"box":{"l":80.25,"t":279.29,"w":20.68,"h":12},"content":"Key","font":2,"fontSize":12},{"id":1879,"type":"word","properties":{},"metadata":[],"box":{"l":104.26,"t":279.29,"w":68.71,"h":12},"content":"configuration","font":2,"fontSize":12},{"id":1880,"type":"word","properties":{},"metadata":[],"box":{"l":176.31,"t":279.29,"w":66.04,"h":12},"content":"environment","font":2,"fontSize":12},{"id":1881,"type":"word","properties":{},"metadata":[],"box":{"l":245.68,"t":279.29,"w":51.36,"h":12},"content":"variables:","font":2,"fontSize":12},{"id":1931,"type":"word","properties":{},"metadata":[],"box":{"l":107.25,"t":311.1,"w":50.41,"h":12},"content":"API_KEY","font":12,"fontSize":12},{"id":1932,"type":"word","properties":{},"metadata":[],"box":{"l":165.5,"t":310.04,"w":4,"h":12},"content":"-","font":2,"fontSize":12},{"id":1933,"type":"word","properties":{},"metadata":[],"box":{"l":172.17,"t":310.04,"w":76.06,"h":12},"content":"Authentication","font":2,"fontSize":12},{"id":1934,"type":"word","properties":{},"metadata":[],"box":{"l":251.56,"t":310.04,"w":29.36,"h":12},"content":"token","font":2,"fontSize":12},{"id":1935,"type":"word","properties":{},"metadata":[],"box":{"l":284.24,"t":310.04,"w":14,"h":12},"content":"for","font":2,"fontSize":12},{"id":1936,"type":"word","properties":{},"metadata":[],"box":{"l":300.92,"t":310.04,"w":19.34,"h":12},"content":"API","font":2,"fontSize":12},{"id":1937,"type":"word","properties":{},"metadata":[],"box":{"l":323.6,"t":310.04,"w":37.35,"h":12},"content":"access","font":2,"fontSize":12},{"id":1938,"type":"word","properties":{},"metadata":[],"box":{"l":364.28,"t":310.04,"w":52.02,"h":12},"content":"(required)","font":2,"fontSize":12},{"id":1980,"type":"word","properties":{},"metadata":[],"box":{"l":107.25,"t":338.1,"w":43.21,"h":12},"content":"DB_URL","font":12,"fontSize":12},{"id":1981,"type":"word","properties":{},"metadata":[],"box":{"l":158.29,"t":337.04,"w":4,"h":12},"content":"-","font":2,"fontSize":12},{"id":1982,"type":"word","properties":{},"metadata":[],"box":{"l":165.62,"t":337.04,"w":51.37,"h":12},"content":"Database","font":2,"fontSize":12},{"id":1983,"type":"word","properties":{},"metadata":[],"box":{"l":220.32,"t":337.04,"w":58.04,"h":12},"content":"connection","font":2,"fontSize":12},{"id":1984,"type":"word","properties":{},"metadata":[],"box":{"l":281.7,"t":337.04,"w":29.34,"h":12},"content":"string","font":2,"fontSize":12},{"id":1985,"type":"word","properties":{},"metadata":[],"box":{"l":314.38,"t":337.04,"w":52.02,"h":12},"content":"(required)","font":2,"fontSize":12},{"id":2307,"type":"word","properties":{},"metadata":[],"box":{"l":384.99,"t":536.54,"w":18.67,"h":12},"content":"file:","font":2,"fontSize":12},{"id":2039,"type":"word","properties":{},"metadata":[],"box":{"l":208.71,"t":363.29,"w":4,"h":12},"content":"-","font":2,"fontSize":12},{"id":2040,"type":"word","properties":{},"metadata":[],"box":{"l":216.04,"t":363.29,"w":26.68,"h":12},"content":"Sync","font":2,"fontSize":12},{"id":2041,"type":"word","properties":{},"metadata":[],"box":{"l":246.05,"t":363.29,"w":31.35,"h":12},"content":"check","font":2,"fontSize":12},{"id":2042,"type":"word","properties":{},"metadata":[],"box":{"l":280.73,"t":363.29,"w":38.68,"h":12},"content":"interval","font":2,"fontSize":12},{"id":2043,"type":"word","properties":{},"metadata":[],"box":{"l":322.75,"t":363.29,"w":9.34,"h":12},"content":"in","font":2,"fontSize":12},{"id":2044,"type":"word","properties":{},"metadata":[],"box":{"l":335.42,"t":363.29,"w":44.69,"h":12},"content":"seconds","font":2,"fontSize":12},{"id":2045,"type":"word","properties":{},"metadata":[],"box":{"l":383.45,"t":363.29,"w":43.36,"h":12},"content":"(default:","font":2,"fontSize":12},{"id":2046,"type":"word","properties":{},"metadata":[],"box":{"l":430.14,"t":363.29,"w":17.34,"h":12},"content":"30)","font":2,"fontSize":12},{"id":2090,"type":"word","properties":{},"metadata":[],"box":{"l":107.25,"t":391.35,"w":79.21,"h":12},"content":"MAX_RETRIES","font":12,"fontSize":12},{"id":2091,"type":"word","properties":{},"metadata":[],"box":{"l":194.3,"t":390.29,"w":4,"h":12},"content":"-","font":2,"fontSize":12},{"id":2092,"type":"word","properties":{},"metadata":[],"box":{"l":201.63,"t":390.29,"w":52,"h":12},"content":"Maximum","font":2,"fontSize":12},{"id":2093,"type":"word","properties":{},"metadata":[],"box":{"l":256.97,"t":390.29,"w":24,"h":12},"content":"retry","font":2,"fontSize":12},{"id":2094,"type":"word","properties":{},"metadata":[],"box":{"l":284.3,"t":390.29,"w":46.02,"h":12},"content":"attempts","font":2,"fontSize":12},{"id":2095,"type":"word","properties":{},"metadata":[],"box":{"l":333.66,"t":390.29,"w":43.36,"h":12},"content":"(default:","font":2,"fontSize":12},{"id":2096,"type":"word","properties":{},"metadata":[],"box":{"l":380.35,"t":390.29,"w":10.67,"h":12},"content":"3)","font":2,"fontSize":12},{"id":2155,"type":"word","properties":{},"metadata":[],"box":{"l":107.25,"t":417.6,"w":108.02,"h":12},"content":"WEBHOOK_TIMEOUT","font":12,"fontSize":12},{"id":2156,"type":"word","properties":{},"metadata":[],"box":{"l":223.11,"t":416.54,"w":4,"h":12},"content":"-","font":2,"fontSize":12},{"id":2157,"type":"word","properties":{},"metadata":[],"box":{"l":230.44,"t":416.54,"w":50.48,"h":12},"content":"Webhook","font":2,"fontSize":12},{"id":2158,"type":"word","properties":{},"metadata":[],"box":{"l":284.25,"t":416.54,"w":40.02,"h":12},"content":"request","font":2,"fontSize":12},{"id":2159,"type":"word","properties":{},"metadata":[],"box":{"l":327.61,"t":416.54,"w":39.35,"h":12},"content":"timeout","font":2,"fontSize":12},{"id":2160,"type":"word","properties":{},"metadata":[],"box":{"l":370.3,"t":416.54,"w":9.34,"h":12},"content":"in","font":2,"fontSize":12},{"id":2161,"type":"word","properties":{},"metadata":[],"box":{"l":382.97,"t":416.54,"w":44.69,"h":12},"content":"seconds","font":2,"fontSize":12},{"id":2162,"type":"word","properties":{},"metadata":[],"box":{"l":431,"t":416.54,"w":43.36,"h":12},"content":"(default:","font":2,"fontSize":12},{"id":2163,"type":"word","properties":{},"metadata":[],"box":{"l":477.69,"t":416.54,"w":17.34,"h":12},"content":"30)","font":2,"fontSize":12},{"id":2217,"type":"word","properties":{},"metadata":[],"box":{"l":107.25,"t":444.6,"w":64.81,"h":12},"content":"LOG_LEVEL","font":12,"fontSize":12},{"id":2218,"type":"word","properties":{},"metadata":[],"box":{"l":179.9,"t":443.54,"w":4,"h":12},"content":"-","font":2,"fontSize":12},{"id":2219,"type":"word","properties":{},"metadata":[],"box":{"l":187.23,"t":443.54,"w":42.71,"h":12},"content":"Logging","font":2,"fontSize":12},{"id":2220,"type":"word","properties":{},"metadata":[],"box":{"l":233.27,"t":443.54,"w":28.01,"h":12},"content":"level:","font":2,"fontSize":12},{"id":2221,"type":"word","properties":{},"metadata":[],"box":{"l":264.62,"t":443.54,"w":46.01,"h":12},"content":"DEBUG,","font":2,"fontSize":12},{"id":2222,"type":"word","properties":{},"metadata":[],"box":{"l":313.96,"t":443.54,"w":32,"h":12},"content":"INFO,","font":2,"fontSize":12},{"id":2223,"type":"word","properties":{},"metadata":[],"box":{"l":349.3,"t":443.54,"w":39.55,"h":12},"content":"WARN,","font":2,"fontSize":12},{"id":2224,"type":"word","properties":{},"metadata":[],"box":{"l":392.18,"t":443.54,"w":43.34,"h":12},"content":"ERROR","font":2,"fontSize":12},{"id":2225,"type":"word","properties":{},"metadata":[],"box":{"l":438.85,"t":443.54,"w":43.36,"h":12},"content":"(default:","font":2,"fontSize":12},{"id":2231,"type":"word","properties":{},"metadata":[],"box":{"l":102.75,"t":464.54,"w":32.66,"h":12},"content":"INFO)","font":2,"fontSize":12},{"id":2249,"type":"word","properties":{},"metadata":[],"box":{"l":80.25,"t":502.4,"w":39.45,"h":14.4},"content":"YAML","font":8,"fontSize":14.4},{"id":2250,"type":"word","properties":{},"metadata":[],"box":{"l":123.44,"t":502.4,"w":94.32,"h":14.4},"content":"Configuration","font":8,"fontSize":14.4},{"id":2301,"type":"word","properties":{},"metadata":[],"box":{"l":80.25,"t":536.54,"w":18,"h":12},"content":"For","font":2,"fontSize":12},{"id":2302,"type":"word","properties":{},"metadata":[],"box":{"l":101.58,"t":536.54,"w":52.04,"h":12},"content":"advanced","font":2,"fontSize":12},{"id":2303,"type":"word","properties":{},"metadata":[],"box":{"l":156.96,"t":536.54,"w":72.05,"h":12},"content":"configuration,","font":2,"fontSize":12},{"id":2304,"type":"word","properties":{},"metadata":[],"box":{"l":232.34,"t":536.54,"w":33.35,"h":12},"content":"create","font":2,"fontSize":12},{"id":2305,"type":"word","properties":{},"metadata":[],"box":{"l":269.03,"t":536.54,"w":6.67,"h":12},"content":"a","font":2,"fontSize":12},{"id":2306,"type":"word","properties":{},"metadata":[],"box":{"l":283.54,"t":537.6,"w":93.61,"h":12},"content":"datasync.yaml","font":12,"fontSize":12},{"id":1687,"type":"word","properties":{},"metadata":[],"box":{"l":138.61,"t":169.04,"w":68.71,"h":12},"content":"configuration","font":2,"fontSize":12}]},{"margins":{"top":164,"left":56,"bottom":624,"right":518},"box":{"l":0,"t":0,"w":595.92,"h":842.88},"rotation":{"degrees":0,"origin":{"x":0,"y":0},"translation":{"x":0,"y":0}},"pageNumber":4,"elements":[{"id":2315,"type":"word","properties":{"isHeader":true},"metadata":[],"box":{"l":95.25,"t":74.94,"w":45.34,"h":10.8},"content":"server:","font":9,"fontSize":10.8},{"id":2407,"type":"word","properties":{},"metadata":[],"box":{"l":153.54,"t":195.69,"w":12.96,"h":10.8},"content":"20","font":9,"fontSize":10.8},{"id":2326,"type":"word","properties":{"isHeader":true},"metadata":[],"box":{"l":147.07,"t":89.94,"w":25.91,"h":10.8},"content":"8080","font":9,"fontSize":10.8},{"id":2338,"type":"word","properties":{"isHeader":true},"metadata":[],"box":{"l":108.2,"t":104.94,"w":51.82,"h":10.8},"content":"timeout:","font":9,"fontSize":10.8},{"id":2339,"type":"word","properties":{"isHeader":true},"metadata":[],"box":{"l":166.5,"t":104.94,"w":19.44,"h":10.8},"content":"30s","font":9,"fontSize":10.8},{"id":2349,"type":"word","properties":{"isHeader":true},"metadata":[],"box":{"l":95.25,"t":135.69,"w":58.3,"h":10.8},"content":"database:","font":9,"fontSize":10.8},{"id":2385,"type":"word","properties":{"isHeader":true},"metadata":[],"box":{"l":108.2,"t":150.69,"w":25.91,"h":10.8},"content":"url:","font":9,"fontSize":10.8},{"id":2386,"type":"word","properties":{"isHeader":true},"metadata":[],"box":{"l":140.59,"t":150.69,"w":200.79,"h":10.8},"content":"postgresql://localhost/datasync","font":9,"fontSize":10.8},{"id":2392,"type":"word","properties":{},"metadata":[],"box":{"l":108.2,"t":165.69,"w":32.39,"h":10.8},"content":"pool:","font":9,"fontSize":10.8},{"id":2398,"type":"word","properties":{},"metadata":[],"box":{"l":121.16,"t":180.69,"w":25.91,"h":10.8},"content":"min:","font":9,"fontSize":10.8},{"id":2399,"type":"word","properties":{},"metadata":[],"box":{"l":153.54,"t":180.69,"w":6.48,"h":10.8},"content":"5","font":9,"fontSize":10.8},{"id":2406,"type":"word","properties":{},"metadata":[],"box":{"l":121.16,"t":195.69,"w":25.91,"h":10.8},"content":"max:","font":9,"fontSize":10.8},{"id":2495,"type":"word","properties":{},"metadata":[],"box":{"l":166.5,"t":332.19,"w":6.48,"h":10.8},"content":"3","font":9,"fontSize":10.8},{"id":2413,"type":"word","properties":{},"metadata":[],"box":{"l":95.25,"t":226.44,"w":32.39,"h":10.8},"content":"sync:","font":9,"fontSize":10.8},{"id":2426,"type":"word","properties":{},"metadata":[],"box":{"l":108.2,"t":241.44,"w":58.3,"h":10.8},"content":"interval:","font":9,"fontSize":10.8},{"id":2427,"type":"word","properties":{},"metadata":[],"box":{"l":172.97,"t":241.44,"w":19.44,"h":10.8},"content":"30s","font":9,"fontSize":10.8},{"id":2440,"type":"word","properties":{},"metadata":[],"box":{"l":108.2,"t":256.44,"w":71.25,"h":10.8},"content":"maxRetries:","font":9,"fontSize":10.8},{"id":2441,"type":"word","properties":{},"metadata":[],"box":{"l":185.93,"t":256.44,"w":6.48,"h":10.8},"content":"3","font":9,"fontSize":10.8},{"id":2461,"type":"word","properties":{},"metadata":[],"box":{"l":108.2,"t":271.44,"w":51.82,"h":10.8},"content":"backoff:","font":9,"fontSize":10.8},{"id":2462,"type":"word","properties":{},"metadata":[],"box":{"l":166.5,"t":271.44,"w":71.25,"h":10.8},"content":"exponential","font":9,"fontSize":10.8},{"id":2471,"type":"word","properties":{},"metadata":[],"box":{"l":95.25,"t":301.44,"w":51.82,"h":10.8},"content":"webhook:","font":9,"fontSize":10.8},{"id":2483,"type":"word","properties":{},"metadata":[],"box":{"l":108.2,"t":317.19,"w":51.82,"h":10.8},"content":"timeout:","font":9,"fontSize":10.8},{"id":2484,"type":"word","properties":{},"metadata":[],"box":{"l":166.5,"t":317.19,"w":19.44,"h":10.8},"content":"30s","font":9,"fontSize":10.8},{"id":2494,"type":"word","properties":{},"metadata":[],"box":{"l":108.2,"t":332.19,"w":51.82,"h":10.8},"content":"retries:","font":9,"fontSize":10.8},{"id":2325,"type":"word","properties":{"isHeader":true},"metadata":[],"box":{"l":108.2,"t":89.94,"w":32.39,"h":10.8},"content":"port:","font":9,"fontSize":10.8}]},{"margins":{"top":164,"left":56,"bottom":624,"right":518},"box":{"l":0,"t":0,"w":595.92,"h":842.88},"rotation":{"degrees":0,"origin":{"x":0,"y":0},"translation":{"x":0,"y":0}},"pageNumber":5,"elements":[{"id":2510,"type":"word","properties":{"isHeader":true},"metadata":[],"box":{"l":80.25,"t":116.87,"w":16.01,"h":19.2},"content":"4.","font":4,"fontSize":19.2},{"id":2905,"type":"word","properties":{},"metadata":[],"box":{"l":342.11,"t":466.04,"w":22.01,"h":12},"content":"new","font":2,"fontSize":12},{"id":2512,"type":"word","properties":{"isHeader":true},"metadata":[],"box":{"l":138.22,"t":116.87,"w":92.83,"h":19.2},"content":"Reference","font":4,"fontSize":19.2},{"id":2576,"type":"word","properties":{},"metadata":[],"box":{"l":80.25,"t":169.04,"w":20.68,"h":12},"content":"The","font":2,"fontSize":12},{"id":2577,"type":"word","properties":{},"metadata":[],"box":{"l":109.21,"t":169.04,"w":52.03,"h":12},"content":"DataSync","font":2,"fontSize":12},{"id":2578,"type":"word","properties":{},"metadata":[],"box":{"l":168.86,"t":169.04,"w":19.34,"h":12},"content":"API","font":2,"fontSize":12},{"id":2579,"type":"word","properties":{},"metadata":[],"box":{"l":196.49,"t":169.04,"w":45.36,"h":12},"content":"provides","font":2,"fontSize":12},{"id":2580,"type":"word","properties":{},"metadata":[],"box":{"l":250.13,"t":169.04,"w":52.04,"h":12},"content":"endpoints","font":2,"fontSize":12},{"id":2581,"type":"word","properties":{},"metadata":[],"box":{"l":310.46,"t":169.04,"w":14,"h":12},"content":"for","font":2,"fontSize":12},{"id":2582,"type":"word","properties":{},"metadata":[],"box":{"l":332.75,"t":169.04,"w":52.7,"h":12},"content":"managing","font":2,"fontSize":12},{"id":2583,"type":"word","properties":{},"metadata":[],"box":{"l":393.74,"t":169.04,"w":83.38,"h":12},"content":"synchronization","font":2,"fontSize":12},{"id":2584,"type":"word","properties":{},"metadata":[],"box":{"l":485.4,"t":169.04,"w":31.34,"h":12},"content":"tasks,","font":2,"fontSize":12},{"id":2659,"type":"word","properties":{},"metadata":[],"box":{"l":80.25,"t":188.54,"w":56.03,"h":12},"content":"monitoring","font":2,"fontSize":12},{"id":2660,"type":"word","properties":{},"metadata":[],"box":{"l":140.9,"t":188.54,"w":35.35,"h":12},"content":"status,","font":2,"fontSize":12},{"id":2661,"type":"word","properties":{},"metadata":[],"box":{"l":180.88,"t":188.54,"w":20.02,"h":12},"content":"and","font":2,"fontSize":12},{"id":2662,"type":"word","properties":{},"metadata":[],"box":{"l":205.52,"t":188.54,"w":49.35,"h":12},"content":"retrieving","font":2,"fontSize":12},{"id":2663,"type":"word","properties":{},"metadata":[],"box":{"l":259.5,"t":188.54,"w":24.67,"h":12},"content":"sync","font":2,"fontSize":12},{"id":2664,"type":"word","properties":{},"metadata":[],"box":{"l":288.8,"t":188.54,"w":38.68,"h":12},"content":"results.","font":2,"fontSize":12},{"id":2665,"type":"word","properties":{},"metadata":[],"box":{"l":331.44,"t":188.54,"w":13.34,"h":12},"content":"All","font":2,"fontSize":12},{"id":2666,"type":"word","properties":{},"metadata":[],"box":{"l":349.4,"t":188.54,"w":46.02,"h":12},"content":"requests","font":2,"fontSize":12},{"id":2667,"type":"word","properties":{},"metadata":[],"box":{"l":400.05,"t":188.54,"w":37.35,"h":12},"content":"require","font":2,"fontSize":12},{"id":2668,"type":"word","properties":{},"metadata":[],"box":{"l":442.03,"t":188.54,"w":74.73,"h":12},"content":"authentication","font":2,"fontSize":12},{"id":2703,"type":"word","properties":{},"metadata":[],"box":{"l":80.25,"t":207.29,"w":15.34,"h":12},"content":"via","font":2,"fontSize":12},{"id":2704,"type":"word","properties":{},"metadata":[],"box":{"l":98.26,"t":207.29,"w":19.34,"h":12},"content":"API","font":2,"fontSize":12},{"id":2705,"type":"word","properties":{},"metadata":[],"box":{"l":120.94,"t":207.29,"w":18.67,"h":12},"content":"key","font":2,"fontSize":12},{"id":2706,"type":"word","properties":{},"metadata":[],"box":{"l":142.95,"t":207.29,"w":9.34,"h":12},"content":"in","font":2,"fontSize":12},{"id":2707,"type":"word","properties":{},"metadata":[],"box":{"l":155.62,"t":207.29,"w":16.68,"h":12},"content":"the","font":2,"fontSize":12},{"id":2708,"type":"word","properties":{},"metadata":[],"box":{"l":180.14,"t":208.35,"w":93.61,"h":12},"content":"Authorization","font":12,"fontSize":12},{"id":2709,"type":"word","properties":{},"metadata":[],"box":{"l":281.6,"t":207.29,"w":40.04,"h":12},"content":"header.","font":2,"fontSize":12},{"id":2724,"type":"word","properties":{},"metadata":[],"box":{"l":80.25,"t":247.4,"w":100.73,"h":14.4},"content":"Authentication","font":8,"fontSize":14.4},{"id":2781,"type":"word","properties":{},"metadata":[],"box":{"l":80.25,"t":280.79,"w":38.69,"h":12},"content":"Include","font":2,"fontSize":12},{"id":2782,"type":"word","properties":{},"metadata":[],"box":{"l":122.28,"t":280.79,"w":23.34,"h":12},"content":"your","font":2,"fontSize":12},{"id":2783,"type":"word","properties":{},"metadata":[],"box":{"l":148.29,"t":280.79,"w":19.34,"h":12},"content":"API","font":2,"fontSize":12},{"id":2784,"type":"word","properties":{},"metadata":[],"box":{"l":170.97,"t":280.79,"w":18.67,"h":12},"content":"key","font":2,"fontSize":12},{"id":2785,"type":"word","properties":{},"metadata":[],"box":{"l":192.98,"t":280.79,"w":9.34,"h":12},"content":"in","font":2,"fontSize":12},{"id":2786,"type":"word","properties":{},"metadata":[],"box":{"l":205.65,"t":280.79,"w":16.68,"h":12},"content":"the","font":2,"fontSize":12},{"id":2787,"type":"word","properties":{},"metadata":[],"box":{"l":230.17,"t":281.85,"w":93.62,"h":12},"content":"Authorization","font":12,"fontSize":12},{"id":2788,"type":"word","properties":{},"metadata":[],"box":{"l":331.62,"t":280.79,"w":37.37,"h":12},"content":"header","font":2,"fontSize":12},{"id":2789,"type":"word","properties":{},"metadata":[],"box":{"l":372.32,"t":280.79,"w":14,"h":12},"content":"for","font":2,"fontSize":12},{"id":2790,"type":"word","properties":{},"metadata":[],"box":{"l":389.66,"t":280.79,"w":12.01,"h":12},"content":"all","font":2,"fontSize":12},{"id":2791,"type":"word","properties":{},"metadata":[],"box":{"l":405,"t":280.79,"w":49.36,"h":12},"content":"requests:","font":2,"fontSize":12},{"id":2829,"type":"word","properties":{},"metadata":[],"box":{"l":95.25,"t":330.69,"w":90.68,"h":10.8},"content":"Authorization:","font":9,"fontSize":10.8},{"id":2830,"type":"word","properties":{},"metadata":[],"box":{"l":192.4,"t":330.69,"w":38.87,"h":10.8},"content":"Bearer","font":9,"fontSize":10.8},{"id":2831,"type":"word","properties":{},"metadata":[],"box":{"l":237.74,"t":330.69,"w":110.11,"h":10.8},"content":"your_api_key_here","font":9,"fontSize":10.8},{"id":2841,"type":"word","properties":{},"metadata":[],"box":{"l":80.25,"t":380.9,"w":70.35,"h":14.4},"content":"Endpoints","font":8,"fontSize":14.4},{"id":2848,"type":"word","properties":{},"metadata":[],"box":{"l":90,"t":428.54,"w":42.66,"h":12},"content":"Method","font":13,"fontSize":12},{"id":2853,"type":"word","properties":{},"metadata":[],"box":{"l":155.34,"t":428.54,"w":26,"h":12},"content":"Path","font":13,"fontSize":12},{"id":2865,"type":"word","properties":{},"metadata":[],"box":{"l":292.75,"t":428.54,"w":66.01,"h":12},"content":"Description","font":13,"fontSize":12},{"id":2874,"type":"word","properties":{},"metadata":[],"box":{"l":427.13,"t":428.54,"w":57.35,"h":12},"content":"Response","font":13,"fontSize":12},{"id":2879,"type":"word","properties":{},"metadata":[],"box":{"l":90,"t":475.04,"w":32.67,"h":12},"content":"POST","font":14,"fontSize":12},{"id":2892,"type":"word","properties":{},"metadata":[],"box":{"l":155.34,"t":475.04,"w":63.36,"h":12},"content":"/api/v1/sync","font":2,"fontSize":12},{"id":2903,"type":"word","properties":{},"metadata":[],"box":{"l":292.75,"t":466.04,"w":36.02,"h":12},"content":"Create","font":2,"fontSize":12},{"id":2904,"type":"word","properties":{},"metadata":[],"box":{"l":332.1,"t":466.04,"w":6.67,"h":12},"content":"a","font":2,"fontSize":12},{"id":3288,"type":"word","properties":{"isFooter":true},"metadata":[],"box":{"l":427.13,"t":732.29,"w":42.03,"h":12},"content":"Content","font":2,"fontSize":12},{"id":2916,"type":"word","properties":{},"metadata":[],"box":{"l":427.13,"t":466.04,"w":20.02,"h":12},"content":"201","font":2,"fontSize":12},{"id":2917,"type":"word","properties":{},"metadata":[],"box":{"l":450.48,"t":466.04,"w":42.69,"h":12},"content":"Created","font":2,"fontSize":12},{"id":2937,"type":"word","properties":{},"metadata":[],"box":{"l":292.75,"t":484.79,"w":83.38,"h":12},"content":"synchronization","font":2,"fontSize":12},{"id":2938,"type":"word","properties":{},"metadata":[],"box":{"l":379.46,"t":484.79,"w":22.01,"h":12},"content":"task","font":2,"fontSize":12},{"id":2949,"type":"word","properties":{},"metadata":[],"box":{"l":427.13,"t":484.79,"w":21.34,"h":12},"content":"with","font":2,"fontSize":12},{"id":2950,"type":"word","properties":{},"metadata":[],"box":{"l":451.8,"t":484.79,"w":24.67,"h":12},"content":"sync","font":2,"fontSize":12},{"id":2951,"type":"word","properties":{},"metadata":[],"box":{"l":479.81,"t":484.79,"w":12,"h":12},"content":"ID","font":2,"fontSize":12},{"id":2955,"type":"word","properties":{},"metadata":[],"box":{"l":90,"t":532.04,"w":24.67,"h":12},"content":"GET","font":14,"fontSize":12},{"id":2973,"type":"word","properties":{},"metadata":[],"box":{"l":155.34,"t":532.04,"w":84.05,"h":12},"content":"/api/v1/sync/{id}","font":2,"fontSize":12},{"id":2990,"type":"word","properties":{},"metadata":[],"box":{"l":292.75,"t":523.04,"w":44.68,"h":12},"content":"Retrieve","font":2,"fontSize":12},{"id":2991,"type":"word","properties":{},"metadata":[],"box":{"l":340.76,"t":523.04,"w":24.67,"h":12},"content":"sync","font":2,"fontSize":12},{"id":2992,"type":"word","properties":{},"metadata":[],"box":{"l":368.77,"t":523.04,"w":22.01,"h":12},"content":"task","font":2,"fontSize":12},{"id":3002,"type":"word","properties":{},"metadata":[],"box":{"l":427.13,"t":523.04,"w":20.02,"h":12},"content":"200","font":2,"fontSize":12},{"id":3003,"type":"word","properties":{},"metadata":[],"box":{"l":450.48,"t":523.04,"w":17.34,"h":12},"content":"OK","font":2,"fontSize":12},{"id":3004,"type":"word","properties":{},"metadata":[],"box":{"l":471.15,"t":523.04,"w":21.34,"h":12},"content":"with","font":2,"fontSize":12},{"id":3021,"type":"word","properties":{},"metadata":[],"box":{"l":292.75,"t":541.79,"w":34.69,"h":12},"content":"details","font":2,"fontSize":12},{"id":3022,"type":"word","properties":{},"metadata":[],"box":{"l":330.77,"t":541.79,"w":20.02,"h":12},"content":"and","font":2,"fontSize":12},{"id":3023,"type":"word","properties":{},"metadata":[],"box":{"l":354.12,"t":541.79,"w":32.02,"h":12},"content":"status","font":2,"fontSize":12},{"id":3034,"type":"word","properties":{},"metadata":[],"box":{"l":427.13,"t":541.79,"w":22.01,"h":12},"content":"task","font":2,"fontSize":12},{"id":3035,"type":"word","properties":{},"metadata":[],"box":{"l":452.47,"t":541.79,"w":32.02,"h":12},"content":"object","font":2,"fontSize":12},{"id":3039,"type":"word","properties":{},"metadata":[],"box":{"l":90,"t":589.79,"w":24.67,"h":12},"content":"GET","font":14,"fontSize":12},{"id":3064,"type":"word","properties":{},"metadata":[],"box":{"l":155.34,"t":589.79,"w":119.4,"h":12},"content":"/api/v1/sync/{id}/status","font":2,"fontSize":12},{"id":3081,"type":"word","properties":{},"metadata":[],"box":{"l":292.75,"t":580.04,"w":19.34,"h":12},"content":"Get","font":2,"fontSize":12},{"id":3082,"type":"word","properties":{},"metadata":[],"box":{"l":315.42,"t":580.04,"w":46.68,"h":12},"content":"real-time","font":2,"fontSize":12},{"id":3083,"type":"word","properties":{},"metadata":[],"box":{"l":365.43,"t":580.04,"w":24.67,"h":12},"content":"sync","font":2,"fontSize":12},{"id":3093,"type":"word","properties":{},"metadata":[],"box":{"l":427.13,"t":580.04,"w":20.02,"h":12},"content":"200","font":2,"fontSize":12},{"id":3094,"type":"word","properties":{},"metadata":[],"box":{"l":450.48,"t":580.04,"w":17.34,"h":12},"content":"OK","font":2,"fontSize":12},{"id":3095,"type":"word","properties":{},"metadata":[],"box":{"l":471.15,"t":580.04,"w":21.34,"h":12},"content":"with","font":2,"fontSize":12},{"id":3109,"type":"word","properties":{},"metadata":[],"box":{"l":292.75,"t":598.79,"w":32.02,"h":12},"content":"status","font":2,"fontSize":12},{"id":3110,"type":"word","properties":{},"metadata":[],"box":{"l":328.1,"t":598.79,"w":42.7,"h":12},"content":"updates","font":2,"fontSize":12},{"id":3123,"type":"word","properties":{},"metadata":[],"box":{"l":427.13,"t":598.79,"w":32.02,"h":12},"content":"status","font":2,"fontSize":12},{"id":3124,"type":"word","properties":{},"metadata":[],"box":{"l":462.48,"t":598.79,"w":32.02,"h":12},"content":"object","font":2,"fontSize":12},{"id":3130,"type":"word","properties":{"isFooter":true},"metadata":[],"box":{"l":90,"t":656.54,"w":39.55,"h":12},"content":"PATCH","font":14,"fontSize":12},{"id":3148,"type":"word","properties":{"isFooter":true},"metadata":[],"box":{"l":155.34,"t":656.54,"w":84.05,"h":12},"content":"/api/v1/sync/{id}","font":2,"fontSize":12},{"id":3164,"type":"word","properties":{"isFooter":true},"metadata":[],"box":{"l":292.75,"t":656.54,"w":83.38,"h":12},"content":"synchronization","font":2,"fontSize":12},{"id":3171,"type":"word","properties":{"isFooter":true},"metadata":[],"box":{"l":292.75,"t":637.04,"w":38.69,"h":12},"content":"Update","font":2,"fontSize":12},{"id":3185,"type":"word","properties":{"isFooter":true},"metadata":[],"box":{"l":292.75,"t":675.29,"w":68.71,"h":12},"content":"configuration","font":2,"fontSize":12},{"id":3195,"type":"word","properties":{"isFooter":true},"metadata":[],"box":{"l":427.13,"t":646.79,"w":20.02,"h":12},"content":"200","font":2,"fontSize":12},{"id":3196,"type":"word","properties":{"isFooter":true},"metadata":[],"box":{"l":450.48,"t":646.79,"w":17.34,"h":12},"content":"OK","font":2,"fontSize":12},{"id":3197,"type":"word","properties":{"isFooter":true},"metadata":[],"box":{"l":471.15,"t":646.79,"w":21.34,"h":12},"content":"with","font":2,"fontSize":12},{"id":3209,"type":"word","properties":{"isFooter":true},"metadata":[],"box":{"l":427.13,"t":665.54,"w":43.38,"h":12},"content":"updated","font":2,"fontSize":12},{"id":3210,"type":"word","properties":{"isFooter":true},"metadata":[],"box":{"l":473.84,"t":665.54,"w":22.01,"h":12},"content":"task","font":2,"fontSize":12},{"id":3217,"type":"word","properties":{"isFooter":true},"metadata":[],"box":{"l":90,"t":723.29,"w":47.34,"h":12},"content":"DELETE","font":14,"fontSize":12},{"id":3235,"type":"word","properties":{"isFooter":true},"metadata":[],"box":{"l":155.34,"t":723.29,"w":84.05,"h":12},"content":"/api/v1/sync/{id}","font":2,"fontSize":12},{"id":3250,"type":"word","properties":{"isFooter":true},"metadata":[],"box":{"l":292.75,"t":713.54,"w":37.35,"h":12},"content":"Cancel","font":2,"fontSize":12},{"id":3251,"type":"word","properties":{"isFooter":true},"metadata":[],"box":{"l":333.43,"t":713.54,"w":13.35,"h":12},"content":"an","font":2,"fontSize":12},{"id":3252,"type":"word","properties":{"isFooter":true},"metadata":[],"box":{"l":350.12,"t":713.54,"w":31.35,"h":12},"content":"active","font":2,"fontSize":12},{"id":3258,"type":"word","properties":{"isFooter":true},"metadata":[],"box":{"l":427.13,"t":713.54,"w":20.02,"h":12},"content":"204","font":2,"fontSize":12},{"id":3259,"type":"word","properties":{"isFooter":true},"metadata":[],"box":{"l":450.48,"t":713.54,"w":15.34,"h":12},"content":"No","font":2,"fontSize":12},{"id":3279,"type":"word","properties":{"isFooter":true},"metadata":[],"box":{"l":292.75,"t":732.29,"w":83.38,"h":12},"content":"synchronization","font":2,"fontSize":12},{"id":3280,"type":"word","properties":{"isFooter":true},"metadata":[],"box":{"l":379.46,"t":732.29,"w":22.01,"h":12},"content":"task","font":2,"fontSize":12},{"id":2511,"type":"word","properties":{"isHeader":true},"metadata":[],"box":{"l":100.89,"t":116.87,"w":32,"h":19.2},"content":"API","font":4,"fontSize":19.2}]},{"margins":{"top":164,"left":56,"bottom":624,"right":518},"box":{"l":0,"t":0,"w":595.92,"h":842.88},"rotation":{"degrees":0,"origin":{"x":0,"y":0},"translation":{"x":0,"y":0}},"pageNumber":6,"elements":[{"id":3309,"type":"word","properties":{},"metadata":[],"box":{"l":121.16,"t":275.94,"w":45.34,"h":10.8},"content":"\"type\":","font":9,"fontSize":10.8},{"id":3726,"type":"word","properties":{},"metadata":[],"box":{"l":172.97,"t":536.19,"w":64.77,"h":10.8},"content":"\"running\",","font":9,"fontSize":10.8},{"id":3351,"type":"word","properties":{},"metadata":[],"box":{"l":121.16,"t":290.94,"w":38.87,"h":10.8},"content":"\"url\":","font":9,"fontSize":10.8},{"id":3352,"type":"word","properties":{},"metadata":[],"box":{"l":166.5,"t":290.94,"w":220.22,"h":10.8},"content":"\"postgresql://source-db:5432/mydb\"","font":9,"fontSize":10.8},{"id":3355,"type":"word","properties":{},"metadata":[],"box":{"l":108.2,"t":305.94,"w":12.96,"h":10.8},"content":"},","font":9,"fontSize":10.8},{"id":3371,"type":"word","properties":{},"metadata":[],"box":{"l":108.2,"t":320.94,"w":90.68,"h":10.8},"content":"\"destination\":","font":9,"fontSize":10.8},{"id":3372,"type":"word","properties":{},"metadata":[],"box":{"l":205.36,"t":320.94,"w":6.48,"h":10.8},"content":"{","font":9,"fontSize":10.8},{"id":3393,"type":"word","properties":{},"metadata":[],"box":{"l":121.16,"t":336.69,"w":45.34,"h":10.8},"content":"\"type\":","font":9,"fontSize":10.8},{"id":3394,"type":"word","properties":{},"metadata":[],"box":{"l":172.97,"t":336.69,"w":84.2,"h":10.8},"content":"\"postgresql\",","font":9,"fontSize":10.8},{"id":3433,"type":"word","properties":{},"metadata":[],"box":{"l":121.16,"t":351.69,"w":38.87,"h":10.8},"content":"\"url\":","font":9,"fontSize":10.8},{"id":3434,"type":"word","properties":{},"metadata":[],"box":{"l":166.5,"t":351.69,"w":207.26,"h":10.8},"content":"\"postgresql://dest-db:5432/mydb\"","font":9,"fontSize":10.8},{"id":3437,"type":"word","properties":{},"metadata":[],"box":{"l":108.2,"t":366.69,"w":12.96,"h":10.8},"content":"},","font":9,"fontSize":10.8},{"id":3472,"type":"word","properties":{},"metadata":[],"box":{"l":108.2,"t":381.69,"w":58.3,"h":10.8},"content":"\"tables\":","font":9,"fontSize":10.8},{"id":3473,"type":"word","properties":{},"metadata":[],"box":{"l":172.97,"t":381.69,"w":58.3,"h":10.8},"content":"[\"users\",","font":9,"fontSize":10.8},{"id":3474,"type":"word","properties":{},"metadata":[],"box":{"l":237.74,"t":381.69,"w":103.63,"h":10.8},"content":"\"transactions\"],","font":9,"fontSize":10.8},{"id":3495,"type":"word","properties":{},"metadata":[],"box":{"l":108.2,"t":396.69,"w":97.16,"h":10.8},"content":"\"syncInterval\":","font":9,"fontSize":10.8},{"id":3496,"type":"word","properties":{},"metadata":[],"box":{"l":211.83,"t":396.69,"w":32.39,"h":10.8},"content":"\"30s\"","font":9,"fontSize":10.8},{"id":3498,"type":"word","properties":{},"metadata":[],"box":{"l":95.25,"t":411.69,"w":6.48,"h":10.8},"content":"}","font":9,"fontSize":10.8},{"id":3509,"type":"word","properties":{},"metadata":[],"box":{"l":108.2,"t":260.94,"w":58.3,"h":10.8},"content":"\"source\":","font":9,"fontSize":10.8},{"id":3510,"type":"word","properties":{},"metadata":[],"box":{"l":172.97,"t":260.94,"w":6.48,"h":10.8},"content":"{","font":9,"fontSize":10.8},{"id":3512,"type":"word","properties":{"writeMode":"vertical"},"metadata":[],"box":{"l":95.25,"t":245.94,"w":6.48,"h":10.8},"content":"{","font":9,"fontSize":10.8},{"id":3537,"type":"word","properties":{},"metadata":[],"box":{"l":95.25,"t":170.19,"w":25.91,"h":10.8},"content":"POST","font":9,"fontSize":10.8},{"id":3538,"type":"word","properties":{},"metadata":[],"box":{"l":127.63,"t":170.19,"w":77.73,"h":10.8},"content":"/api/v1/sync","font":9,"fontSize":10.8},{"id":3539,"type":"word","properties":{},"metadata":[],"box":{"l":211.83,"t":170.19,"w":51.82,"h":10.8},"content":"HTTP/1.1","font":9,"fontSize":10.8},{"id":3560,"type":"word","properties":{},"metadata":[],"box":{"l":95.25,"t":185.19,"w":32.39,"h":10.8},"content":"Host:","font":9,"fontSize":10.8},{"id":3561,"type":"word","properties":{},"metadata":[],"box":{"l":134.11,"t":185.19,"w":97.16,"h":10.8},"content":"api.datasync.io","font":9,"fontSize":10.8},{"id":3594,"type":"word","properties":{},"metadata":[],"box":{"l":95.25,"t":200.19,"w":90.68,"h":10.8},"content":"Authorization:","font":9,"fontSize":10.8},{"id":3595,"type":"word","properties":{},"metadata":[],"box":{"l":192.4,"t":200.19,"w":38.87,"h":10.8},"content":"Bearer","font":9,"fontSize":10.8},{"id":3596,"type":"word","properties":{},"metadata":[],"box":{"l":237.74,"t":200.19,"w":77.73,"h":10.8},"content":"your_api_key","font":9,"fontSize":10.8},{"id":3626,"type":"word","properties":{},"metadata":[],"box":{"l":95.25,"t":215.19,"w":84.2,"h":10.8},"content":"Content-Type:","font":9,"fontSize":10.8},{"id":3627,"type":"word","properties":{},"metadata":[],"box":{"l":185.93,"t":215.19,"w":103.63,"h":10.8},"content":"application/json","font":9,"fontSize":10.8},{"id":3651,"type":"word","properties":{"isHeader":true},"metadata":[],"box":{"l":80.25,"t":61.4,"w":59.2,"h":14.4},"content":"Example","font":8,"fontSize":14.4},{"id":3652,"type":"word","properties":{"isHeader":true},"metadata":[],"box":{"l":143.44,"t":61.4,"w":129.56,"h":14.4},"content":"Request/Response","font":8,"fontSize":14.4},{"id":3667,"type":"word","properties":{"isHeader":true},"metadata":[],"box":{"l":80.25,"t":95.54,"w":37.35,"h":12},"content":"Create","font":15,"fontSize":12},{"id":3668,"type":"word","properties":{"isHeader":true},"metadata":[],"box":{"l":120.94,"t":95.54,"w":28.68,"h":12},"content":"Sync","font":15,"fontSize":12},{"id":3669,"type":"word","properties":{"isHeader":true},"metadata":[],"box":{"l":152.95,"t":95.54,"w":26.46,"h":12},"content":"Task","font":15,"fontSize":12},{"id":3678,"type":"word","properties":{"isHeader":true},"metadata":[],"box":{"l":80.25,"t":121.79,"w":48.03,"h":12},"content":"Request:","font":2,"fontSize":12},{"id":3704,"type":"word","properties":{},"metadata":[],"box":{"l":108.2,"t":521.19,"w":32.39,"h":10.8},"content":"\"id\":","font":9,"fontSize":10.8},{"id":3705,"type":"word","properties":{},"metadata":[],"box":{"l":147.07,"t":521.19,"w":129.54,"h":10.8},"content":"\"sync_abc123xyz789\",","font":9,"fontSize":10.8},{"id":3725,"type":"word","properties":{},"metadata":[],"box":{"l":108.2,"t":536.19,"w":58.3,"h":10.8},"content":"\"status\":","font":9,"fontSize":10.8},{"id":4059,"type":"word","properties":{"isFooter":true},"metadata":[],"box":{"l":415.34,"t":758.1,"w":86.41,"h":12},"content":"X-RateLimit-","font":12,"fontSize":12},{"id":3740,"type":"word","properties":{},"metadata":[],"box":{"l":108.2,"t":551.94,"w":71.25,"h":10.8},"content":"\"progress\":","font":9,"fontSize":10.8},{"id":3741,"type":"word","properties":{},"metadata":[],"box":{"l":185.93,"t":551.94,"w":12.96,"h":10.8},"content":"0,","font":9,"fontSize":10.8},{"id":3777,"type":"word","properties":{},"metadata":[],"box":{"l":108.2,"t":566.94,"w":77.73,"h":10.8},"content":"\"createdAt\":","font":9,"fontSize":10.8},{"id":3778,"type":"word","properties":{},"metadata":[],"box":{"l":192.4,"t":566.94,"w":148.97,"h":10.8},"content":"\"2026-02-21T10:30:00Z\",","font":9,"fontSize":10.8},{"id":3794,"type":"word","properties":{},"metadata":[],"box":{"l":108.2,"t":581.94,"w":58.3,"h":10.8},"content":"\"source\":","font":9,"fontSize":10.8},{"id":3795,"type":"word","properties":{},"metadata":[],"box":{"l":172.97,"t":581.94,"w":38.86,"h":10.8},"content":"{...},","font":9,"fontSize":10.8},{"id":3816,"type":"word","properties":{},"metadata":[],"box":{"l":108.2,"t":596.94,"w":90.68,"h":10.8},"content":"\"destination\":","font":9,"fontSize":10.8},{"id":3817,"type":"word","properties":{},"metadata":[],"box":{"l":205.36,"t":596.94,"w":38.87,"h":10.8},"content":"{...},","font":9,"fontSize":10.8},{"id":3852,"type":"word","properties":{},"metadata":[],"box":{"l":108.2,"t":611.94,"w":58.3,"h":10.8},"content":"\"tables\":","font":9,"fontSize":10.8},{"id":3853,"type":"word","properties":{},"metadata":[],"box":{"l":172.97,"t":611.94,"w":58.3,"h":10.8},"content":"[\"users\",","font":9,"fontSize":10.8},{"id":3854,"type":"word","properties":{},"metadata":[],"box":{"l":237.74,"t":611.94,"w":103.63,"h":10.8},"content":"\"transactions\"],","font":9,"fontSize":10.8},{"id":3882,"type":"word","properties":{"isFooter":true},"metadata":[],"box":{"l":108.2,"t":626.94,"w":129.54,"h":10.8},"content":"\"estimatedDuration\":","font":9,"fontSize":10.8},{"id":3883,"type":"word","properties":{"isFooter":true},"metadata":[],"box":{"l":244.22,"t":626.94,"w":45.34,"h":10.8},"content":"\"2m45s\"","font":9,"fontSize":10.8},{"id":3885,"type":"word","properties":{"isFooter":true},"metadata":[],"box":{"l":95.25,"t":642.69,"w":6.48,"h":10.8},"content":"}","font":9,"fontSize":10.8},{"id":3887,"type":"word","properties":{"writeMode":"vertical"},"metadata":[],"box":{"l":95.25,"t":506.19,"w":6.48,"h":10.8},"content":"{","font":9,"fontSize":10.8},{"id":3909,"type":"word","properties":{},"metadata":[],"box":{"l":80.25,"t":458.54,"w":54.04,"h":12},"content":"Response","font":2,"fontSize":12},{"id":3910,"type":"word","properties":{},"metadata":[],"box":{"l":137.62,"t":458.54,"w":24.02,"h":12},"content":"(201","font":2,"fontSize":12},{"id":3911,"type":"word","properties":{},"metadata":[],"box":{"l":164.97,"t":458.54,"w":50.02,"h":12},"content":"Created):","font":2,"fontSize":12},{"id":3925,"type":"word","properties":{"isFooter":true},"metadata":[],"box":{"l":98.25,"t":711.29,"w":20,"h":12},"content":"API","font":6,"fontSize":12},{"id":3926,"type":"word","properties":{"isFooter":true},"metadata":[],"box":{"l":121.59,"t":711.29,"w":26.01,"h":12},"content":"Rate","font":6,"fontSize":12},{"id":3927,"type":"word","properties":{"isFooter":true},"metadata":[],"box":{"l":150.93,"t":711.29,"w":35.34,"h":12},"content":"Limits","font":6,"fontSize":12},{"id":3990,"type":"word","properties":{"isFooter":true},"metadata":[],"box":{"l":98.25,"t":737.54,"w":52.03,"h":12},"content":"DataSync","font":5,"fontSize":12},{"id":3991,"type":"word","properties":{"isFooter":true},"metadata":[],"box":{"l":153.41,"t":737.54,"w":19.34,"h":12},"content":"API","font":5,"fontSize":12},{"id":3992,"type":"word","properties":{"isFooter":true},"metadata":[],"box":{"l":176.54,"t":737.54,"w":46.03,"h":12},"content":"enforces","font":5,"fontSize":12},{"id":3993,"type":"word","properties":{"isFooter":true},"metadata":[],"box":{"l":226.36,"t":737.54,"w":20.68,"h":12},"content":"rate","font":5,"fontSize":12},{"id":3994,"type":"word","properties":{"isFooter":true},"metadata":[],"box":{"l":250.83,"t":737.54,"w":27.33,"h":12},"content":"limits","font":5,"fontSize":12},{"id":3995,"type":"word","properties":{"isFooter":true},"metadata":[],"box":{"l":281.96,"t":737.54,"w":10.01,"h":12},"content":"of","font":5,"fontSize":12},{"id":3996,"type":"word","properties":{"isFooter":true},"metadata":[],"box":{"l":295.76,"t":737.54,"w":26.69,"h":12},"content":"1000","font":5,"fontSize":12},{"id":3997,"type":"word","properties":{"isFooter":true},"metadata":[],"box":{"l":326.25,"t":737.54,"w":46.02,"h":12},"content":"requests","font":5,"fontSize":12},{"id":3998,"type":"word","properties":{"isFooter":true},"metadata":[],"box":{"l":376.07,"t":737.54,"w":17.34,"h":12},"content":"per","font":5,"fontSize":12},{"id":3999,"type":"word","properties":{"isFooter":true},"metadata":[],"box":{"l":397.2,"t":737.54,"w":36.02,"h":12},"content":"minute","font":5,"fontSize":12},{"id":4000,"type":"word","properties":{"isFooter":true},"metadata":[],"box":{"l":437.02,"t":737.54,"w":17.34,"h":12},"content":"per","font":5,"fontSize":12},{"id":4001,"type":"word","properties":{"isFooter":true},"metadata":[],"box":{"l":457.49,"t":737.54,"w":19.34,"h":12},"content":"API","font":5,"fontSize":12},{"id":4002,"type":"word","properties":{"isFooter":true},"metadata":[],"box":{"l":480.63,"t":737.54,"w":21.12,"h":12},"content":"key.","font":5,"fontSize":12},{"id":4055,"type":"word","properties":{"isFooter":true},"metadata":[],"box":{"l":98.25,"t":757.04,"w":60.04,"h":12},"content":"Responses","font":5,"fontSize":12},{"id":4056,"type":"word","properties":{"isFooter":true},"metadata":[],"box":{"l":166.85,"t":757.04,"w":38.03,"h":12},"content":"include","font":5,"fontSize":12},{"id":4057,"type":"word","properties":{"isFooter":true},"metadata":[],"box":{"l":217.95,"t":758.1,"w":151.23,"h":12},"content":"X-RateLimit-Remaining","font":12,"fontSize":12},{"id":4058,"type":"word","properties":{"isFooter":true},"metadata":[],"box":{"l":382.24,"t":757.04,"w":20.02,"h":12},"content":"and","font":5,"fontSize":12},{"id":3310,"type":"word","properties":{},"metadata":[],"box":{"l":172.97,"t":275.94,"w":84.2,"h":10.8},"content":"\"postgresql\",","font":9,"fontSize":10.8}]},{"margins":{"top":164,"left":56,"bottom":624,"right":518},"box":{"l":0,"t":0,"w":595.92,"h":842.88},"rotation":{"degrees":0,"origin":{"x":0,"y":0},"translation":{"x":0,"y":0}},"pageNumber":7,"elements":[{"id":4097,"type":"word","properties":{"isHeader":true},"metadata":[],"box":{"l":98.25,"t":62.1,"w":36.01,"h":12},"content":"Reset","font":12,"fontSize":12},{"id":4517,"type":"word","properties":{},"metadata":[],"box":{"l":206.22,"t":469.04,"w":37.37,"h":12},"content":"header","font":2,"fontSize":12},{"id":4099,"type":"word","properties":{"isHeader":true},"metadata":[],"box":{"l":188.8,"t":61.04,"w":10.01,"h":12},"content":"to","font":5,"fontSize":12},{"id":4100,"type":"word","properties":{"isHeader":true},"metadata":[],"box":{"l":202.14,"t":61.04,"w":22.69,"h":12},"content":"help","font":5,"fontSize":12},{"id":4101,"type":"word","properties":{"isHeader":true},"metadata":[],"box":{"l":228.16,"t":61.04,"w":19.35,"h":12},"content":"you","font":5,"fontSize":12},{"id":4102,"type":"word","properties":{"isHeader":true},"metadata":[],"box":{"l":250.84,"t":61.04,"w":43.36,"h":12},"content":"manage","font":5,"fontSize":12},{"id":4103,"type":"word","properties":{"isHeader":true},"metadata":[],"box":{"l":297.54,"t":61.04,"w":23.34,"h":12},"content":"your","font":5,"fontSize":12},{"id":4104,"type":"word","properties":{"isHeader":true},"metadata":[],"box":{"l":324.22,"t":61.04,"w":33.36,"h":12},"content":"quota.","font":5,"fontSize":12},{"id":4122,"type":"word","properties":{},"metadata":[],"box":{"l":80.25,"t":213.62,"w":16.01,"h":19.2},"content":"5.","font":4,"fontSize":19.2},{"id":4123,"type":"word","properties":{},"metadata":[],"box":{"l":101.6,"t":213.62,"w":150.35,"h":19.2},"content":"Troubleshooting","font":4,"fontSize":19.2},{"id":4154,"type":"word","properties":{},"metadata":[],"box":{"l":80.25,"t":265.79,"w":48.68,"h":12},"content":"Common","font":2,"fontSize":12},{"id":4155,"type":"word","properties":{},"metadata":[],"box":{"l":132.26,"t":265.79,"w":34.01,"h":12},"content":"issues","font":2,"fontSize":12},{"id":4156,"type":"word","properties":{},"metadata":[],"box":{"l":169.61,"t":265.79,"w":20.02,"h":12},"content":"and","font":2,"fontSize":12},{"id":4157,"type":"word","properties":{},"metadata":[],"box":{"l":192.97,"t":265.79,"w":23.34,"h":12},"content":"their","font":2,"fontSize":12},{"id":4158,"type":"word","properties":{},"metadata":[],"box":{"l":219.65,"t":265.79,"w":50.69,"h":12},"content":"solutions:","font":2,"fontSize":12},{"id":4176,"type":"word","properties":{},"metadata":[],"box":{"l":80.25,"t":303.65,"w":79.15,"h":14.4},"content":"Connection","font":8,"fontSize":14.4},{"id":4177,"type":"word","properties":{},"metadata":[],"box":{"l":163.39,"t":303.65,"w":55.7,"h":14.4},"content":"Timeout","font":8,"fontSize":14.4},{"id":4207,"type":"word","properties":{},"metadata":[],"box":{"l":80.25,"t":377.54,"w":80.7,"h":12},"content":"communication","font":2,"fontSize":12},{"id":4208,"type":"word","properties":{},"metadata":[],"box":{"l":164.29,"t":377.54,"w":13.35,"h":12},"content":"on","font":2,"fontSize":12},{"id":4209,"type":"word","properties":{},"metadata":[],"box":{"l":180.97,"t":377.54,"w":44.03,"h":12},"content":"required","font":2,"fontSize":12},{"id":4210,"type":"word","properties":{},"metadata":[],"box":{"l":228.33,"t":377.54,"w":30.01,"h":12},"content":"ports.","font":2,"fontSize":12},{"id":4231,"type":"word","properties":{},"metadata":[],"box":{"l":80.25,"t":416.15,"w":100.73,"h":14.4},"content":"Authentication","font":8,"fontSize":14.4},{"id":4232,"type":"word","properties":{},"metadata":[],"box":{"l":184.98,"t":416.15,"w":43.2,"h":14.4},"content":"Errors","font":8,"fontSize":14.4},{"id":4297,"type":"word","properties":{},"metadata":[],"box":{"l":80.25,"t":337.79,"w":6.67,"h":12},"content":"If","font":2,"fontSize":12},{"id":4298,"type":"word","properties":{},"metadata":[],"box":{"l":92.84,"t":337.79,"w":24.67,"h":12},"content":"sync","font":2,"fontSize":12},{"id":4299,"type":"word","properties":{},"metadata":[],"box":{"l":123.43,"t":337.79,"w":28.01,"h":12},"content":"tasks","font":2,"fontSize":12},{"id":4300,"type":"word","properties":{},"metadata":[],"box":{"l":157.35,"t":337.79,"w":42.68,"h":12},"content":"timeout,","font":2,"fontSize":12},{"id":4301,"type":"word","properties":{},"metadata":[],"box":{"l":205.96,"t":337.79,"w":45.36,"h":12},"content":"increase","font":2,"fontSize":12},{"id":4302,"type":"word","properties":{},"metadata":[],"box":{"l":257.23,"t":337.79,"w":16.68,"h":12},"content":"the","font":2,"fontSize":12},{"id":4303,"type":"word","properties":{},"metadata":[],"box":{"l":284.33,"t":338.85,"w":108.02,"h":12},"content":"WEBHOOK_TIMEOUT","font":12,"fontSize":12},{"id":4304,"type":"word","properties":{},"metadata":[],"box":{"l":402.77,"t":337.79,"w":66.04,"h":12},"content":"environment","font":2,"fontSize":12},{"id":4305,"type":"word","properties":{},"metadata":[],"box":{"l":474.73,"t":337.79,"w":42.02,"h":12},"content":"variable","font":2,"fontSize":12},{"id":4373,"type":"word","properties":{},"metadata":[],"box":{"l":80.25,"t":358.04,"w":20.02,"h":12},"content":"and","font":2,"fontSize":12},{"id":4374,"type":"word","properties":{},"metadata":[],"box":{"l":106.83,"t":358.04,"w":31.35,"h":12},"content":"check","font":2,"fontSize":12},{"id":4375,"type":"word","properties":{},"metadata":[],"box":{"l":144.73,"t":358.04,"w":42.02,"h":12},"content":"network","font":2,"fontSize":12},{"id":4376,"type":"word","properties":{},"metadata":[],"box":{"l":193.3,"t":358.04,"w":62.69,"h":12},"content":"connectivity","font":2,"fontSize":12},{"id":4377,"type":"word","properties":{},"metadata":[],"box":{"l":262.55,"t":358.04,"w":45.37,"h":12},"content":"between","font":2,"fontSize":12},{"id":4378,"type":"word","properties":{},"metadata":[],"box":{"l":314.47,"t":358.04,"w":47.34,"h":12},"content":"services.","font":2,"fontSize":12},{"id":4379,"type":"word","properties":{},"metadata":[],"box":{"l":368.37,"t":358.04,"w":38.02,"h":12},"content":"Ensure","font":2,"fontSize":12},{"id":4380,"type":"word","properties":{},"metadata":[],"box":{"l":412.95,"t":358.04,"w":37.34,"h":12},"content":"firewall","font":2,"fontSize":12},{"id":4381,"type":"word","properties":{},"metadata":[],"box":{"l":456.84,"t":358.04,"w":26.01,"h":12},"content":"rules","font":2,"fontSize":12},{"id":4382,"type":"word","properties":{},"metadata":[],"box":{"l":489.4,"t":358.04,"w":27.35,"h":12},"content":"allow","font":2,"fontSize":12},{"id":4452,"type":"word","properties":{},"metadata":[],"box":{"l":80.25,"t":449.54,"w":30.01,"h":12},"content":"Verify","font":2,"fontSize":12},{"id":4453,"type":"word","properties":{},"metadata":[],"box":{"l":113.86,"t":449.54,"w":23.34,"h":12},"content":"your","font":2,"fontSize":12},{"id":4454,"type":"word","properties":{},"metadata":[],"box":{"l":140.14,"t":449.54,"w":19.34,"h":12},"content":"API","font":2,"fontSize":12},{"id":4455,"type":"word","properties":{},"metadata":[],"box":{"l":163.08,"t":449.54,"w":18.67,"h":12},"content":"key","font":2,"fontSize":12},{"id":4456,"type":"word","properties":{},"metadata":[],"box":{"l":185.36,"t":449.54,"w":8.67,"h":12},"content":"is","font":2,"fontSize":12},{"id":4457,"type":"word","properties":{},"metadata":[],"box":{"l":197.62,"t":449.54,"w":36.67,"h":12},"content":"correct","font":2,"fontSize":12},{"id":4458,"type":"word","properties":{},"metadata":[],"box":{"l":237.9,"t":449.54,"w":20.02,"h":12},"content":"and","font":2,"fontSize":12},{"id":4459,"type":"word","properties":{},"metadata":[],"box":{"l":261.52,"t":449.54,"w":31.65,"h":12},"content":"hasn't","font":2,"fontSize":12},{"id":4460,"type":"word","properties":{},"metadata":[],"box":{"l":296.76,"t":449.54,"w":42.69,"h":12},"content":"expired.","font":2,"fontSize":12},{"id":4461,"type":"word","properties":{},"metadata":[],"box":{"l":343.06,"t":449.54,"w":34.01,"h":12},"content":"Check","font":2,"fontSize":12},{"id":4462,"type":"word","properties":{},"metadata":[],"box":{"l":380.67,"t":449.54,"w":20.02,"h":12},"content":"that","font":2,"fontSize":12},{"id":4463,"type":"word","properties":{},"metadata":[],"box":{"l":404.28,"t":449.54,"w":16.68,"h":12},"content":"the","font":2,"fontSize":12},{"id":4464,"type":"word","properties":{},"metadata":[],"box":{"l":424.56,"t":449.54,"w":18.67,"h":12},"content":"key","font":2,"fontSize":12},{"id":4465,"type":"word","properties":{},"metadata":[],"box":{"l":446.84,"t":449.54,"w":8.67,"h":12},"content":"is","font":2,"fontSize":12},{"id":4466,"type":"word","properties":{},"metadata":[],"box":{"l":459.1,"t":449.54,"w":44.7,"h":12},"content":"included","font":2,"fontSize":12},{"id":4467,"type":"word","properties":{},"metadata":[],"box":{"l":507.4,"t":449.54,"w":9.34,"h":12},"content":"in","font":2,"fontSize":12},{"id":4515,"type":"word","properties":{},"metadata":[],"box":{"l":80.25,"t":469.04,"w":16.68,"h":12},"content":"the","font":2,"fontSize":12},{"id":4516,"type":"word","properties":{},"metadata":[],"box":{"l":104.77,"t":470.1,"w":93.62,"h":12},"content":"Authorization","font":12,"fontSize":12},{"id":4973,"type":"word","properties":{"isFooter":true},"metadata":[],"box":{"l":255.67,"t":703.04,"w":66.72,"h":12},"content":"degradation.","font":10,"fontSize":12},{"id":4518,"type":"word","properties":{},"metadata":[],"box":{"l":246.92,"t":469.04,"w":21.34,"h":12},"content":"with","font":2,"fontSize":12},{"id":4519,"type":"word","properties":{},"metadata":[],"box":{"l":271.59,"t":469.04,"w":16.68,"h":12},"content":"the","font":2,"fontSize":12},{"id":4520,"type":"word","properties":{},"metadata":[],"box":{"l":291.61,"t":469.04,"w":34.01,"h":12},"content":"format","font":2,"fontSize":12},{"id":4521,"type":"word","properties":{},"metadata":[],"box":{"l":333.46,"t":470.1,"w":43.21,"h":12},"content":"Bearer","font":12,"fontSize":12},{"id":4522,"type":"word","properties":{},"metadata":[],"box":{"l":383.87,"t":469.04,"w":43.84,"h":13.06},"content":"<key>.","font":12,"fontSize":12},{"id":4547,"type":"word","properties":{},"metadata":[],"box":{"l":80.25,"t":509.15,"w":64,"h":14.4},"content":"Database","font":8,"fontSize":14.4},{"id":4548,"type":"word","properties":{},"metadata":[],"box":{"l":148.24,"t":509.15,"w":79.15,"h":14.4},"content":"Connection","font":8,"fontSize":14.4},{"id":4549,"type":"word","properties":{},"metadata":[],"box":{"l":231.38,"t":509.15,"w":44.81,"h":14.4},"content":"Issues","font":8,"fontSize":14.4},{"id":4621,"type":"word","properties":{},"metadata":[],"box":{"l":80.25,"t":542.54,"w":22.01,"h":12},"content":"Test","font":2,"fontSize":12},{"id":4622,"type":"word","properties":{},"metadata":[],"box":{"l":108.37,"t":542.54,"w":49.38,"h":12},"content":"database","font":2,"fontSize":12},{"id":4623,"type":"word","properties":{},"metadata":[],"box":{"l":163.87,"t":542.54,"w":62.7,"h":12},"content":"connectivity","font":2,"fontSize":12},{"id":4624,"type":"word","properties":{},"metadata":[],"box":{"l":232.68,"t":542.54,"w":28.69,"h":12},"content":"using","font":2,"fontSize":12},{"id":4625,"type":"word","properties":{},"metadata":[],"box":{"l":267.48,"t":542.54,"w":46.7,"h":12},"content":"standard","font":2,"fontSize":12},{"id":4626,"type":"word","properties":{},"metadata":[],"box":{"l":320.3,"t":542.54,"w":49.38,"h":12},"content":"database","font":2,"fontSize":12},{"id":4627,"type":"word","properties":{},"metadata":[],"box":{"l":375.79,"t":542.54,"w":37.35,"h":12},"content":"clients.","font":2,"fontSize":12},{"id":4628,"type":"word","properties":{},"metadata":[],"box":{"l":419.25,"t":542.54,"w":30.01,"h":12},"content":"Verify","font":2,"fontSize":12},{"id":4629,"type":"word","properties":{},"metadata":[],"box":{"l":455.38,"t":542.54,"w":61.37,"h":12},"content":"credentials,","font":2,"fontSize":12},{"id":4695,"type":"word","properties":{},"metadata":[],"box":{"l":80.25,"t":562.04,"w":56.03,"h":12},"content":"hostname,","font":2,"fontSize":12},{"id":4696,"type":"word","properties":{},"metadata":[],"box":{"l":141.3,"t":562.04,"w":20.02,"h":12},"content":"and","font":2,"fontSize":12},{"id":4697,"type":"word","properties":{},"metadata":[],"box":{"l":166.35,"t":562.04,"w":20.68,"h":12},"content":"port","font":2,"fontSize":12},{"id":4698,"type":"word","properties":{},"metadata":[],"box":{"l":192.04,"t":562.04,"w":9.34,"h":12},"content":"in","font":2,"fontSize":12},{"id":4699,"type":"word","properties":{},"metadata":[],"box":{"l":206.4,"t":562.04,"w":16.68,"h":12},"content":"the","font":2,"fontSize":12},{"id":4700,"type":"word","properties":{},"metadata":[],"box":{"l":228.11,"t":562.04,"w":58.04,"h":12},"content":"connection","font":2,"fontSize":12},{"id":4701,"type":"word","properties":{},"metadata":[],"box":{"l":291.17,"t":562.04,"w":32.68,"h":12},"content":"string.","font":2,"fontSize":12},{"id":4702,"type":"word","properties":{},"metadata":[],"box":{"l":328.87,"t":562.04,"w":34.01,"h":12},"content":"Check","font":2,"fontSize":12},{"id":4703,"type":"word","properties":{},"metadata":[],"box":{"l":367.9,"t":562.04,"w":20.02,"h":12},"content":"that","font":2,"fontSize":12},{"id":4704,"type":"word","properties":{},"metadata":[],"box":{"l":392.94,"t":562.04,"w":16.68,"h":12},"content":"the","font":2,"fontSize":12},{"id":4705,"type":"word","properties":{},"metadata":[],"box":{"l":414.64,"t":562.04,"w":49.38,"h":12},"content":"database","font":2,"fontSize":12},{"id":4706,"type":"word","properties":{},"metadata":[],"box":{"l":469.04,"t":562.04,"w":23.34,"h":12},"content":"user","font":2,"fontSize":12},{"id":4707,"type":"word","properties":{},"metadata":[],"box":{"l":497.4,"t":562.04,"w":19.35,"h":12},"content":"has","font":2,"fontSize":12},{"id":4754,"type":"word","properties":{},"metadata":[],"box":{"l":80.25,"t":580.79,"w":60.71,"h":12},"content":"appropriate","font":2,"fontSize":12},{"id":4755,"type":"word","properties":{},"metadata":[],"box":{"l":144.29,"t":580.79,"w":64.02,"h":12},"content":"permissions","font":2,"fontSize":12},{"id":4756,"type":"word","properties":{},"metadata":[],"box":{"l":211.65,"t":580.79,"w":14,"h":12},"content":"for","font":2,"fontSize":12},{"id":4757,"type":"word","properties":{},"metadata":[],"box":{"l":228.98,"t":580.79,"w":52.69,"h":12},"content":"read/write","font":2,"fontSize":12},{"id":4758,"type":"word","properties":{},"metadata":[],"box":{"l":285.01,"t":580.79,"w":59.37,"h":12},"content":"operations.","font":2,"fontSize":12},{"id":4784,"type":"word","properties":{"isFooter":true},"metadata":[],"box":{"l":98.25,"t":637.79,"w":73.37,"h":12},"content":"Performance","font":11,"fontSize":12},{"id":4785,"type":"word","properties":{"isFooter":true},"metadata":[],"box":{"l":174.95,"t":637.79,"w":87.35,"h":12},"content":"Considerations","font":11,"fontSize":12},{"id":4850,"type":"word","properties":{"isFooter":true},"metadata":[],"box":{"l":98.25,"t":664.79,"w":18,"h":12},"content":"For","font":10,"fontSize":12},{"id":4851,"type":"word","properties":{"isFooter":true},"metadata":[],"box":{"l":119.75,"t":664.79,"w":26.68,"h":12},"content":"large","font":10,"fontSize":12},{"id":4852,"type":"word","properties":{"isFooter":true},"metadata":[],"box":{"l":149.93,"t":664.79,"w":45.36,"h":12},"content":"datasets","font":10,"fontSize":12},{"id":4853,"type":"word","properties":{"isFooter":true},"metadata":[],"box":{"l":198.79,"t":664.79,"w":54.71,"h":12},"content":"exceeding","font":10,"fontSize":12},{"id":4854,"type":"word","properties":{"isFooter":true},"metadata":[],"box":{"l":256.99,"t":664.79,"w":27.35,"h":12},"content":"1GB,","font":10,"fontSize":12},{"id":4855,"type":"word","properties":{"isFooter":true},"metadata":[],"box":{"l":287.83,"t":664.79,"w":45.36,"h":12},"content":"consider","font":10,"fontSize":12},{"id":4856,"type":"word","properties":{"isFooter":true},"metadata":[],"box":{"l":336.69,"t":664.79,"w":71.37,"h":12},"content":"implementing","font":10,"fontSize":12},{"id":4857,"type":"word","properties":{"isFooter":true},"metadata":[],"box":{"l":411.55,"t":664.79,"w":62.03,"h":12},"content":"incremental","font":10,"fontSize":12},{"id":4858,"type":"word","properties":{"isFooter":true},"metadata":[],"box":{"l":477.08,"t":664.79,"w":24.67,"h":12},"content":"sync","font":10,"fontSize":12},{"id":4922,"type":"word","properties":{"isFooter":true},"metadata":[],"box":{"l":98.25,"t":683.54,"w":52.03,"h":12},"content":"strategies","font":10,"fontSize":12},{"id":4923,"type":"word","properties":{"isFooter":true},"metadata":[],"box":{"l":154.94,"t":683.54,"w":20.02,"h":12},"content":"and","font":10,"fontSize":12},{"id":4924,"type":"word","properties":{"isFooter":true},"metadata":[],"box":{"l":179.62,"t":683.54,"w":45.38,"h":12},"content":"enabling","font":10,"fontSize":12},{"id":4925,"type":"word","properties":{"isFooter":true},"metadata":[],"box":{"l":229.66,"t":683.54,"w":71.36,"h":12},"content":"compression.","font":10,"fontSize":12},{"id":4926,"type":"word","properties":{"isFooter":true},"metadata":[],"box":{"l":305.68,"t":683.54,"w":40.01,"h":12},"content":"Monitor","font":10,"fontSize":12},{"id":4927,"type":"word","properties":{"isFooter":true},"metadata":[],"box":{"l":350.35,"t":683.54,"w":46.69,"h":12},"content":"resource","font":10,"fontSize":12},{"id":4928,"type":"word","properties":{"isFooter":true},"metadata":[],"box":{"l":401.7,"t":683.54,"w":32.69,"h":12},"content":"usage","font":10,"fontSize":12},{"id":4929,"type":"word","properties":{"isFooter":true},"metadata":[],"box":{"l":439.06,"t":683.54,"w":33.36,"h":12},"content":"during","font":10,"fontSize":12},{"id":4930,"type":"word","properties":{"isFooter":true},"metadata":[],"box":{"l":477.08,"t":683.54,"w":24.67,"h":12},"content":"sync","font":10,"fontSize":12},{"id":4969,"type":"word","properties":{"isFooter":true},"metadata":[],"box":{"l":98.25,"t":703.04,"w":56.04,"h":12},"content":"operations","font":10,"fontSize":12},{"id":4970,"type":"word","properties":{"isFooter":true},"metadata":[],"box":{"l":157.62,"t":703.04,"w":10.01,"h":12},"content":"to","font":10,"fontSize":12},{"id":4971,"type":"word","properties":{"isFooter":true},"metadata":[],"box":{"l":170.97,"t":703.04,"w":40.03,"h":12},"content":"prevent","font":10,"fontSize":12},{"id":4972,"type":"word","properties":{"isFooter":true},"metadata":[],"box":{"l":214.32,"t":703.04,"w":38.01,"h":12},"content":"service","font":10,"fontSize":12},{"id":4098,"type":"word","properties":{"isHeader":true},"metadata":[],"box":{"l":142.1,"t":61.04,"w":43.37,"h":12},"content":"headers","font":5,"fontSize":12}]}],"fonts":[{"id":1,"name":"AAAAAA+LiberationSans-Bold","size":30,"weight":"bold","isItalic":false,"isUnderline":false,"color":"#1b3b5d","sizeUnit":"px"},{"id":2,"name":"BAAAAA+LiberationSans","size":12,"weight":"medium","isItalic":false,"isUnderline":false,"color":"#333333","sizeUnit":"px"},{"id":3,"name":"BAAAAA+LiberationSans","size":11.4,"weight":"medium","isItalic":false,"isUnderline":false,"color":"#787878","sizeUnit":"px"},{"id":4,"name":"AAAAAA+LiberationSans-Bold","size":19.2,"weight":"bold","isItalic":false,"isUnderline":false,"color":"#1b3b5d","sizeUnit":"px"},{"id":5,"name":"BAAAAA+LiberationSans","size":12,"weight":"medium","isItalic":false,"isUnderline":false,"color":"#17a186","sizeUnit":"px"},{"id":6,"name":"AAAAAA+LiberationSans-Bold","size":12,"weight":"bold","isItalic":false,"isUnderline":false,"color":"#2a81ba","sizeUnit":"px"},{"id":7,"name":"BAAAAA+LiberationSans","size":12,"weight":"medium","isItalic":false,"isUnderline":false,"color":"#2a81ba","sizeUnit":"px"},{"id":8,"name":"AAAAAA+LiberationSans-Bold","size":14.4,"weight":"bold","isItalic":false,"isUnderline":false,"color":"#2c3e50","sizeUnit":"px"},{"id":9,"name":"CAAAAA+LiberationMono","size":10.8,"weight":"medium","isItalic":false,"isUnderline":false,"color":"#d5d5d5","sizeUnit":"px"},{"id":10,"name":"BAAAAA+LiberationSans","size":12,"weight":"medium","isItalic":false,"isUnderline":false,"color":"#a93326","sizeUnit":"px"},{"id":11,"name":"AAAAAA+LiberationSans-Bold","size":12,"weight":"bold","isItalic":false,"isUnderline":false,"color":"#c0392b","sizeUnit":"px"},{"id":12,"name":"CAAAAA+LiberationMono","size":12,"weight":"medium","isItalic":false,"isUnderline":false,"color":"#c0392b","sizeUnit":"px"},{"id":13,"name":"AAAAAA+LiberationSans-Bold","size":12,"weight":"bold","isItalic":false,"isUnderline":false,"color":"#ffffff","sizeUnit":"px"},{"id":14,"name":"AAAAAA+LiberationSans-Bold","size":12,"weight":"bold","isItalic":false,"isUnderline":false,"color":"#333333","sizeUnit":"px"},{"id":15,"name":"AAAAAA+LiberationSans-Bold","size":12,"weight":"bold","isItalic":false,"isUnderline":false,"color":"#344a5e","sizeUnit":"px"}]}